{
"meta":{"test_sets":[],"test_metrics":[],"learn_metrics":[{"best_value":"Min","name":"MultiClass"}],"launch_mode":"Train","parameters":"","iteration_count":1000,"learn_sets":["learn"],"name":"experiment"},
"iterations":[
{"learn":[1.330217329],"iteration":0,"passed_time":0.02536596525,"remaining_time":25.34059929},
{"learn":[1.287876206],"iteration":1,"passed_time":0.04307485927,"remaining_time":21.49435478},
{"learn":[1.255125794],"iteration":2,"passed_time":0.06088132846,"remaining_time":20.23289482},
{"learn":[1.229141395],"iteration":3,"passed_time":0.07844376972,"remaining_time":19.53249866},
{"learn":[1.208593728],"iteration":4,"passed_time":0.09361865908,"remaining_time":18.63011316},
{"learn":[1.191649701],"iteration":5,"passed_time":0.1123781811,"remaining_time":18.61731867},
{"learn":[1.177885669],"iteration":6,"passed_time":0.1346149112,"remaining_time":19.09608668},
{"learn":[1.166451078],"iteration":7,"passed_time":0.157968066,"remaining_time":19.58804018},
{"learn":[1.157313603],"iteration":8,"passed_time":0.1788883711,"remaining_time":19.69759731},
{"learn":[1.149735281],"iteration":9,"passed_time":0.2012182166,"remaining_time":19.92060344},
{"learn":[1.143383609],"iteration":10,"passed_time":0.229208632,"remaining_time":20.60793973},
{"learn":[1.138455273],"iteration":11,"passed_time":0.2479651142,"remaining_time":20.4157944},
{"learn":[1.133982916],"iteration":12,"passed_time":0.2663338256,"remaining_time":20.22088353},
{"learn":[1.130424805],"iteration":13,"passed_time":0.2862081325,"remaining_time":20.1572299},
{"learn":[1.126866121],"iteration":14,"passed_time":0.3143199019,"remaining_time":20.64034023},
{"learn":[1.123972579],"iteration":15,"passed_time":0.3437009286,"remaining_time":21.13760711},
{"learn":[1.1215787],"iteration":16,"passed_time":0.3666035857,"remaining_time":21.19831322},
{"learn":[1.11974933],"iteration":17,"passed_time":0.3900030882,"remaining_time":21.27683514},
{"learn":[1.118196395],"iteration":18,"passed_time":0.4153088264,"remaining_time":21.44305046},
{"learn":[1.116470617],"iteration":19,"passed_time":0.4408813815,"remaining_time":21.60318769},
{"learn":[1.115129612],"iteration":20,"passed_time":0.462662644,"remaining_time":21.56889183},
{"learn":[1.11389926],"iteration":21,"passed_time":0.4850076287,"remaining_time":21.56079368},
{"learn":[1.112938646],"iteration":22,"passed_time":0.5068332491,"remaining_time":21.52939497},
{"learn":[1.111783792],"iteration":23,"passed_time":0.5288945378,"remaining_time":21.50837787},
{"learn":[1.110861992],"iteration":24,"passed_time":0.550663401,"remaining_time":21.47587264},
{"learn":[1.109873307],"iteration":25,"passed_time":0.5760939531,"remaining_time":21.58136578},
{"learn":[1.109136517],"iteration":26,"passed_time":0.5965004836,"remaining_time":21.49611002},
{"learn":[1.108627427],"iteration":27,"passed_time":0.6147907489,"remaining_time":21.34202171},
{"learn":[1.108063266],"iteration":28,"passed_time":0.638967943,"remaining_time":21.3944094},
{"learn":[1.107335864],"iteration":29,"passed_time":0.6627078786,"remaining_time":21.42755474},
{"learn":[1.106631901],"iteration":30,"passed_time":0.6858434942,"remaining_time":21.43814019},
{"learn":[1.106041735],"iteration":31,"passed_time":0.7068752639,"remaining_time":21.38297673},
{"learn":[1.105685335],"iteration":32,"passed_time":0.7266701547,"remaining_time":21.29363756},
{"learn":[1.105095493],"iteration":33,"passed_time":0.748881706,"remaining_time":21.27705082},
{"learn":[1.104737267],"iteration":34,"passed_time":0.7676354283,"remaining_time":21.16480538},
{"learn":[1.104287569],"iteration":35,"passed_time":0.7894118011,"remaining_time":21.13869379},
{"learn":[1.103943569],"iteration":36,"passed_time":0.8102509303,"remaining_time":21.08842286},
{"learn":[1.103616221],"iteration":37,"passed_time":0.8366285355,"remaining_time":21.17991187},
{"learn":[1.103320319],"iteration":38,"passed_time":0.8592440568,"remaining_time":21.17265484},
{"learn":[1.102857631],"iteration":39,"passed_time":0.8809673223,"remaining_time":21.14321573},
{"learn":[1.102418436],"iteration":40,"passed_time":0.9064528416,"remaining_time":21.20215305},
{"learn":[1.102013464],"iteration":41,"passed_time":0.9263489974,"remaining_time":21.12957951},
{"learn":[1.101630174],"iteration":42,"passed_time":0.9477809073,"remaining_time":21.09363554},
{"learn":[1.101382581],"iteration":43,"passed_time":0.9682389353,"remaining_time":21.03719141},
{"learn":[1.100967249],"iteration":44,"passed_time":0.9880064175,"remaining_time":20.96769175},
{"learn":[1.100684423],"iteration":45,"passed_time":1.005610807,"remaining_time":20.85549369},
{"learn":[1.100289515],"iteration":46,"passed_time":1.025943741,"remaining_time":20.80264649},
{"learn":[1.099971064],"iteration":47,"passed_time":1.050320995,"remaining_time":20.8313664},
{"learn":[1.099444664],"iteration":48,"passed_time":1.080371479,"remaining_time":20.96802604},
{"learn":[1.099092975],"iteration":49,"passed_time":1.102522273,"remaining_time":20.94792318},
{"learn":[1.098840251],"iteration":50,"passed_time":1.121932643,"remaining_time":20.87674663},
{"learn":[1.0984124],"iteration":51,"passed_time":1.146303867,"remaining_time":20.89800127},
{"learn":[1.097976867],"iteration":52,"passed_time":1.1741518,"remaining_time":20.97965574},
{"learn":[1.097678214],"iteration":53,"passed_time":1.193232156,"remaining_time":20.90365962},
{"learn":[1.097355241],"iteration":54,"passed_time":1.213193618,"remaining_time":20.84487217},
{"learn":[1.097125305],"iteration":55,"passed_time":1.247460123,"remaining_time":21.02861351},
{"learn":[1.096832059],"iteration":56,"passed_time":1.276222201,"remaining_time":21.11364097},
{"learn":[1.096663201],"iteration":57,"passed_time":1.300137378,"remaining_time":21.11602431},
{"learn":[1.096388183],"iteration":58,"passed_time":1.327631928,"remaining_time":21.17460413},
{"learn":[1.096109868],"iteration":59,"passed_time":1.356645702,"remaining_time":21.25411601},
{"learn":[1.095939891],"iteration":60,"passed_time":1.378757399,"remaining_time":21.22382291},
{"learn":[1.095581429],"iteration":61,"passed_time":1.401847337,"remaining_time":21.20859358},
{"learn":[1.09526765],"iteration":62,"passed_time":1.438939002,"remaining_time":21.40136261},
{"learn":[1.095109459],"iteration":63,"passed_time":1.461295396,"remaining_time":21.37144517},
{"learn":[1.094824175],"iteration":64,"passed_time":1.481377123,"remaining_time":21.30904015},
{"learn":[1.094640904],"iteration":65,"passed_time":1.501382043,"remaining_time":21.24683073},
{"learn":[1.09431466],"iteration":66,"passed_time":1.521304557,"remaining_time":21.18473361},
{"learn":[1.093942412],"iteration":67,"passed_time":1.546601796,"remaining_time":21.19754226},
{"learn":[1.093733918],"iteration":68,"passed_time":1.566679473,"remaining_time":21.13882014},
{"learn":[1.09340019],"iteration":69,"passed_time":1.588849346,"remaining_time":21.10899846},
{"learn":[1.093141611],"iteration":70,"passed_time":1.609516514,"remaining_time":21.05973016},
{"learn":[1.092998162],"iteration":71,"passed_time":1.634336436,"remaining_time":21.06478073},
{"learn":[1.092802105],"iteration":72,"passed_time":1.656880531,"remaining_time":21.04011305},
{"learn":[1.092632646],"iteration":73,"passed_time":1.677820035,"remaining_time":20.99542369},
{"learn":[1.092471687],"iteration":74,"passed_time":1.69997127,"remaining_time":20.96631233},
{"learn":[1.092301241],"iteration":75,"passed_time":1.719708333,"remaining_time":20.90803289},
{"learn":[1.092091277],"iteration":76,"passed_time":1.740882836,"remaining_time":20.86798516},
{"learn":[1.091870936],"iteration":77,"passed_time":1.762131215,"remaining_time":20.82929462},
{"learn":[1.091664504],"iteration":78,"passed_time":1.782522746,"remaining_time":20.78105632},
{"learn":[1.091444078],"iteration":79,"passed_time":1.803294719,"remaining_time":20.73788926},
{"learn":[1.091257568],"iteration":80,"passed_time":1.822746336,"remaining_time":20.68029485},
{"learn":[1.091017821],"iteration":81,"passed_time":1.843790205,"remaining_time":20.6414562},
{"learn":[1.090850117],"iteration":82,"passed_time":1.867533901,"remaining_time":20.63287454},
{"learn":[1.090738242],"iteration":83,"passed_time":1.887099153,"remaining_time":20.57836696},
{"learn":[1.090479383],"iteration":84,"passed_time":1.909008449,"remaining_time":20.54991449},
{"learn":[1.090290761],"iteration":85,"passed_time":1.928522594,"remaining_time":20.49615873},
{"learn":[1.090028907],"iteration":86,"passed_time":1.950198752,"remaining_time":20.46587886},
{"learn":[1.089716576],"iteration":87,"passed_time":1.971405593,"remaining_time":20.43093069},
{"learn":[1.089532572],"iteration":88,"passed_time":1.991768856,"remaining_time":20.38765649},
{"learn":[1.089410571],"iteration":89,"passed_time":2.012148488,"remaining_time":20.34505693},
{"learn":[1.089219153],"iteration":90,"passed_time":2.033571958,"remaining_time":20.31337263},
{"learn":[1.089128925],"iteration":91,"passed_time":2.0511134,"remaining_time":20.24359747},
{"learn":[1.089007084],"iteration":92,"passed_time":2.069285741,"remaining_time":20.18109857},
{"learn":[1.088793513],"iteration":93,"passed_time":2.09135246,"remaining_time":20.15707796},
{"learn":[1.088675755],"iteration":94,"passed_time":2.112462895,"remaining_time":20.12398864},
{"learn":[1.08849205],"iteration":95,"passed_time":2.135963863,"remaining_time":20.11365971},
{"learn":[1.088321803],"iteration":96,"passed_time":2.154966033,"remaining_time":20.06117864},
{"learn":[1.088219735],"iteration":97,"passed_time":2.171617029,"remaining_time":19.98774041},
{"learn":[1.088027569],"iteration":98,"passed_time":2.194431611,"remaining_time":19.97154426},
{"learn":[1.087804311],"iteration":99,"passed_time":2.213405492,"remaining_time":19.92064943},
{"learn":[1.087635254],"iteration":100,"passed_time":2.232973974,"remaining_time":19.87567924},
{"learn":[1.087455503],"iteration":101,"passed_time":2.254743937,"remaining_time":19.85058878},
{"learn":[1.087201544],"iteration":102,"passed_time":2.2781328,"remaining_time":19.83966138},
{"learn":[1.087039371],"iteration":103,"passed_time":2.298827737,"remaining_time":19.80528512},
{"learn":[1.086902221],"iteration":104,"passed_time":2.321468007,"remaining_time":19.78775111},
{"learn":[1.086802668],"iteration":105,"passed_time":2.341467658,"remaining_time":19.74784987},
{"learn":[1.086594245],"iteration":106,"passed_time":2.362681778,"remaining_time":19.71845634},
{"learn":[1.086305789],"iteration":107,"passed_time":2.38549352,"remaining_time":19.70240944},
{"learn":[1.08613443],"iteration":108,"passed_time":2.40468538,"remaining_time":19.65664838},
{"learn":[1.085973525],"iteration":109,"passed_time":2.429989849,"remaining_time":19.66082696},
{"learn":[1.085829625],"iteration":110,"passed_time":2.45320966,"remaining_time":19.64777827},
{"learn":[1.085685332],"iteration":111,"passed_time":2.479324188,"remaining_time":19.65749892},
{"learn":[1.085542249],"iteration":112,"passed_time":2.498588615,"remaining_time":19.61281506},
{"learn":[1.085408316],"iteration":113,"passed_time":2.519163458,"remaining_time":19.57876161},
{"learn":[1.085243555],"iteration":114,"passed_time":2.544890625,"remaining_time":19.58459307},
{"learn":[1.085125336],"iteration":115,"passed_time":2.563003079,"remaining_time":19.53185105},
{"learn":[1.084962465],"iteration":116,"passed_time":2.585579762,"remaining_time":19.51339257},
{"learn":[1.084761385],"iteration":117,"passed_time":2.609836652,"remaining_time":19.50742311},
{"learn":[1.084576124],"iteration":118,"passed_time":2.632104211,"remaining_time":19.48641857},
{"learn":[1.084357444],"iteration":119,"passed_time":2.653216687,"remaining_time":19.45692237},
{"learn":[1.084182552],"iteration":120,"passed_time":2.673193658,"remaining_time":19.41931592},
{"learn":[1.084060419],"iteration":121,"passed_time":2.69418426,"remaining_time":19.38929328},
{"learn":[1.083944472],"iteration":122,"passed_time":2.716131134,"remaining_time":19.36623581},
{"learn":[1.083804107],"iteration":123,"passed_time":2.736509386,"remaining_time":19.3321147},
{"learn":[1.083595614],"iteration":124,"passed_time":2.760315869,"remaining_time":19.32221108},
{"learn":[1.083430521],"iteration":125,"passed_time":2.782378927,"remaining_time":19.29999351},
{"learn":[1.083175092],"iteration":126,"passed_time":2.807767972,"remaining_time":19.30064125},
{"learn":[1.082999968],"iteration":127,"passed_time":2.832199163,"remaining_time":19.2943568},
{"learn":[1.082862628],"iteration":128,"passed_time":2.850527106,"remaining_time":19.24658225},
{"learn":[1.082674705],"iteration":129,"passed_time":2.869823602,"remaining_time":19.20574257},
{"learn":[1.08256962],"iteration":130,"passed_time":2.889955266,"remaining_time":19.17077196},
{"learn":[1.082390365],"iteration":131,"passed_time":2.911897621,"remaining_time":19.14793284},
{"learn":[1.082277011],"iteration":132,"passed_time":2.931898291,"remaining_time":19.11244976},
{"learn":[1.082148352],"iteration":133,"passed_time":2.950895062,"remaining_time":19.07070988},
{"learn":[1.082051044],"iteration":134,"passed_time":2.970355519,"remaining_time":19.03227796},
{"learn":[1.081809864],"iteration":135,"passed_time":2.993321723,"remaining_time":19.01639683},
{"learn":[1.081627881],"iteration":136,"passed_time":3.012659726,"remaining_time":18.97755726},
{"learn":[1.081457902],"iteration":137,"passed_time":3.035333425,"remaining_time":18.95983632},
{"learn":[1.081294933],"iteration":138,"passed_time":3.056178274,"remaining_time":18.93071578},
{"learn":[1.081078084],"iteration":139,"passed_time":3.078476501,"remaining_time":18.91064136},
{"learn":[1.080902646],"iteration":140,"passed_time":3.09749054,"remaining_time":18.87052748},
{"learn":[1.080769936],"iteration":141,"passed_time":3.119012136,"remaining_time":18.84586206},
{"learn":[1.080609756],"iteration":142,"passed_time":3.14155656,"remaining_time":18.82737044},
{"learn":[1.080497962],"iteration":143,"passed_time":3.160834007,"remaining_time":18.78940215},
{"learn":[1.08029493],"iteration":144,"passed_time":3.182710265,"remaining_time":18.7670157},
{"learn":[1.080085756],"iteration":145,"passed_time":3.202725745,"remaining_time":18.73375196},
{"learn":[1.079938729],"iteration":146,"passed_time":3.22364799,"remaining_time":18.70593017},
{"learn":[1.079760502],"iteration":147,"passed_time":3.24426182,"remaining_time":18.67642615},
{"learn":[1.079605748],"iteration":148,"passed_time":3.263719978,"remaining_time":18.64044095},
{"learn":[1.079448093],"iteration":149,"passed_time":3.28368655,"remaining_time":18.60755712},
{"learn":[1.079318991],"iteration":150,"passed_time":3.30409536,"remaining_time":18.57733087},
{"learn":[1.07920088],"iteration":151,"passed_time":3.326293402,"remaining_time":18.55721582},
{"learn":[1.079107714],"iteration":152,"passed_time":3.344644185,"remaining_time":18.51577532},
{"learn":[1.078951723],"iteration":153,"passed_time":3.366331662,"remaining_time":18.49296484},
{"learn":[1.078795349],"iteration":154,"passed_time":3.389509225,"remaining_time":18.47829223},
{"learn":[1.07864972],"iteration":155,"passed_time":3.40862764,"remaining_time":18.44154954},
{"learn":[1.078480722],"iteration":156,"passed_time":3.433375955,"remaining_time":18.4352607},
{"learn":[1.07831301],"iteration":157,"passed_time":3.464384852,"remaining_time":18.46210155},
{"learn":[1.078173097],"iteration":158,"passed_time":3.491462822,"remaining_time":18.46742285},
{"learn":[1.078059226],"iteration":159,"passed_time":3.512425485,"remaining_time":18.4402338},
{"learn":[1.077916942],"iteration":160,"passed_time":3.53497665,"remaining_time":18.42140006},
{"learn":[1.077815769],"iteration":161,"passed_time":3.55559845,"remaining_time":18.39254013},
{"learn":[1.077689571],"iteration":162,"passed_time":3.572799579,"remaining_time":18.34621624},
{"learn":[1.077579574],"iteration":163,"passed_time":3.593964662,"remaining_time":18.32045401},
{"learn":[1.077462726],"iteration":164,"passed_time":3.616266939,"remaining_time":18.30050239},
{"learn":[1.077233329],"iteration":165,"passed_time":3.636778374,"remaining_time":18.27152508},
{"learn":[1.077147473],"iteration":166,"passed_time":3.657439122,"remaining_time":18.24339394},
{"learn":[1.077033634],"iteration":167,"passed_time":3.677663602,"remaining_time":18.21319117},
{"learn":[1.076939927],"iteration":168,"passed_time":3.697787856,"remaining_time":18.18261366},
{"learn":[1.076833919],"iteration":169,"passed_time":3.721901633,"remaining_time":18.17163739},
{"learn":[1.076702821],"iteration":170,"passed_time":3.747597622,"remaining_time":18.16817795},
{"learn":[1.076564338],"iteration":171,"passed_time":3.771748208,"remaining_time":18.15702044},
{"learn":[1.07638013],"iteration":172,"passed_time":3.794926231,"remaining_time":18.14106354},
{"learn":[1.076176793],"iteration":173,"passed_time":3.819506745,"remaining_time":18.13168145},
{"learn":[1.076067447],"iteration":174,"passed_time":3.842623012,"remaining_time":18.11522277},
{"learn":[1.075915847],"iteration":175,"passed_time":3.865026293,"remaining_time":18.09535037},
{"learn":[1.075763112],"iteration":176,"passed_time":3.892484995,"remaining_time":18.09895566},
{"learn":[1.075602763],"iteration":177,"passed_time":3.917093888,"remaining_time":18.08905155},
{"learn":[1.075498135],"iteration":178,"passed_time":3.939657272,"remaining_time":18.06960123},
{"learn":[1.075382053],"iteration":179,"passed_time":3.962440085,"remaining_time":18.05111594},
{"learn":[1.075213709],"iteration":180,"passed_time":3.983452925,"remaining_time":18.02457429},
{"learn":[1.075078645],"iteration":181,"passed_time":4.005667127,"remaining_time":18.00349291},
{"learn":[1.074919676],"iteration":182,"passed_time":4.026786572,"remaining_time":17.97751164},
{"learn":[1.07480758],"iteration":183,"passed_time":4.045211161,"remaining_time":17.9396321},
{"learn":[1.074673441],"iteration":184,"passed_time":4.068511268,"remaining_time":17.92344153},
{"learn":[1.074576433],"iteration":185,"passed_time":4.089720579,"remaining_time":17.89802447},
{"learn":[1.074449983],"iteration":186,"passed_time":4.110944639,"remaining_time":17.87271653},
{"learn":[1.074347783],"iteration":187,"passed_time":4.12971989,"remaining_time":17.83687527},
{"learn":[1.074205132],"iteration":188,"passed_time":4.14934336,"remaining_time":17.80485431},
{"learn":[1.07408714],"iteration":189,"passed_time":4.169762549,"remaining_time":17.77635613},
{"learn":[1.073975166],"iteration":190,"passed_time":4.191324503,"remaining_time":17.75278284},
{"learn":[1.073896917],"iteration":191,"passed_time":4.21281287,"remaining_time":17.72892083},
{"learn":[1.073769197],"iteration":192,"passed_time":4.236759175,"remaining_time":17.7153609},
{"learn":[1.073607068],"iteration":193,"passed_time":4.25769687,"remaining_time":17.68919421},
{"learn":[1.073385351],"iteration":194,"passed_time":4.277682411,"remaining_time":17.65915047},
{"learn":[1.07330239],"iteration":195,"passed_time":4.294130248,"remaining_time":17.61469755},
{"learn":[1.073230833],"iteration":196,"passed_time":4.311847451,"remaining_time":17.57570306},
{"learn":[1.073164411],"iteration":197,"passed_time":4.33310156,"remaining_time":17.55124975},
{"learn":[1.073049469],"iteration":198,"passed_time":4.352032613,"remaining_time":17.51747801},
{"learn":[1.072932355],"iteration":199,"passed_time":4.370803185,"remaining_time":17.48321274},
{"learn":[1.07277914],"iteration":200,"passed_time":4.391568268,"remaining_time":17.45703008},
{"learn":[1.072647848],"iteration":201,"passed_time":4.418931814,"remaining_time":17.45696826},
{"learn":[1.072531102],"iteration":202,"passed_time":4.437442009,"remaining_time":17.42187823},
{"learn":[1.072433051],"iteration":203,"passed_time":4.455281076,"remaining_time":17.38433204},
{"learn":[1.072305872],"iteration":204,"passed_time":4.475033019,"remaining_time":17.35439634},
{"learn":[1.07214811],"iteration":205,"passed_time":4.496398432,"remaining_time":17.33077842},
{"learn":[1.072070736],"iteration":206,"passed_time":4.52555288,"remaining_time":17.33702142},
{"learn":[1.071936664],"iteration":207,"passed_time":4.543889663,"remaining_time":17.30173372},
{"learn":[1.071814448],"iteration":208,"passed_time":4.566244967,"remaining_time":17.28181708},
{"learn":[1.071696367],"iteration":209,"passed_time":4.588742694,"remaining_time":17.26241299},
{"learn":[1.071612034],"iteration":210,"passed_time":4.610194793,"remaining_time":17.23906963},
{"learn":[1.071487664],"iteration":211,"passed_time":4.636709992,"remaining_time":17.23456355},
{"learn":[1.071424835],"iteration":212,"passed_time":4.654392587,"remaining_time":17.1972158},
{"learn":[1.071290515],"iteration":213,"passed_time":4.676181179,"remaining_time":17.17513274},
{"learn":[1.071236283],"iteration":214,"passed_time":4.698759812,"remaining_time":17.15593699},
{"learn":[1.071176943],"iteration":215,"passed_time":4.72022869,"remaining_time":17.13268191},
{"learn":[1.071039654],"iteration":216,"passed_time":4.742213323,"remaining_time":17.11130429},
{"learn":[1.070893],"iteration":217,"passed_time":4.7637059,"remaining_time":17.08815603},
{"learn":[1.070778516],"iteration":218,"passed_time":4.784162008,"remaining_time":17.06132661},
{"learn":[1.07063821],"iteration":219,"passed_time":4.80332339,"remaining_time":17.02996475},
{"learn":[1.070572091],"iteration":220,"passed_time":4.823565069,"remaining_time":17.00252121},
{"learn":[1.070496562],"iteration":221,"passed_time":4.845737692,"remaining_time":16.98190957},
{"learn":[1.070344792],"iteration":222,"passed_time":4.868259168,"remaining_time":16.96249943},
{"learn":[1.070266831],"iteration":223,"passed_time":4.888082347,"remaining_time":16.93371385},
{"learn":[1.070145733],"iteration":224,"passed_time":4.90905697,"remaining_time":16.90897401},
{"learn":[1.070045923],"iteration":225,"passed_time":4.928180964,"remaining_time":16.8779295},
{"learn":[1.069880519],"iteration":226,"passed_time":4.950581556,"remaining_time":16.85814776},
{"learn":[1.069846109],"iteration":227,"passed_time":4.969788056,"remaining_time":16.82752798},
{"learn":[1.069728505],"iteration":228,"passed_time":4.989240043,"remaining_time":16.79783438},
{"learn":[1.069637958],"iteration":229,"passed_time":5.006953457,"remaining_time":16.7624094},
{"learn":[1.069502875],"iteration":230,"passed_time":5.028549119,"remaining_time":16.74006179},
{"learn":[1.069316825],"iteration":231,"passed_time":5.0509672,"remaining_time":16.72044314},
{"learn":[1.069239265],"iteration":232,"passed_time":5.068853475,"remaining_time":16.68588247},
{"learn":[1.069144588],"iteration":233,"passed_time":5.0895737,"remaining_time":16.66074126},
{"learn":[1.069062018],"iteration":234,"passed_time":5.122166268,"remaining_time":16.67428594},
{"learn":[1.068963279],"iteration":235,"passed_time":5.146312294,"remaining_time":16.66009573},
{"learn":[1.068864594],"iteration":236,"passed_time":5.166641888,"remaining_time":16.63353485},
{"learn":[1.068749668],"iteration":237,"passed_time":5.189203582,"remaining_time":16.61417281},
{"learn":[1.068659291],"iteration":238,"passed_time":5.208886788,"remaining_time":16.5856186},
{"learn":[1.068429447],"iteration":239,"passed_time":5.23330976,"remaining_time":16.57214757},
{"learn":[1.068296891],"iteration":240,"passed_time":5.256145461,"remaining_time":16.55358674},
{"learn":[1.068136519],"iteration":241,"passed_time":5.287394625,"remaining_time":16.56134349},
{"learn":[1.0680136],"iteration":242,"passed_time":5.314472796,"remaining_time":16.55578562},
{"learn":[1.067907843],"iteration":243,"passed_time":5.34067266,"remaining_time":16.54733004},
{"learn":[1.067748672],"iteration":244,"passed_time":5.363996716,"remaining_time":16.52986743},
{"learn":[1.067674168],"iteration":245,"passed_time":5.386211457,"remaining_time":16.50895707},
{"learn":[1.067635294],"iteration":246,"passed_time":5.425120662,"remaining_time":16.5389306},
{"learn":[1.067545124],"iteration":247,"passed_time":5.446668496,"remaining_time":16.51570447},
{"learn":[1.067464162],"iteration":248,"passed_time":5.473924628,"remaining_time":16.50970842},
{"learn":[1.067346748],"iteration":249,"passed_time":5.497006866,"remaining_time":16.4910206},
{"learn":[1.067253679],"iteration":250,"passed_time":5.521280436,"remaining_time":16.47585277},
{"learn":[1.067167468],"iteration":251,"passed_time":5.544060259,"remaining_time":16.45617886},
{"learn":[1.0671105],"iteration":252,"passed_time":5.566306748,"remaining_time":16.4349057},
{"learn":[1.066970928],"iteration":253,"passed_time":5.594236507,"remaining_time":16.43031667},
{"learn":[1.066882008],"iteration":254,"passed_time":5.616534934,"remaining_time":16.40909226},
{"learn":[1.066778919],"iteration":255,"passed_time":5.639086588,"remaining_time":16.3885954},
{"learn":[1.066685057],"iteration":256,"passed_time":5.661028973,"remaining_time":16.36632112},
{"learn":[1.06657547],"iteration":257,"passed_time":5.685173299,"remaining_time":16.35038212},
{"learn":[1.066518299],"iteration":258,"passed_time":5.708959712,"remaining_time":16.33335578},
{"learn":[1.066379486],"iteration":259,"passed_time":5.730886487,"remaining_time":16.31098462},
{"learn":[1.066248589],"iteration":260,"passed_time":5.751784304,"remaining_time":16.28570345},
{"learn":[1.066151486],"iteration":261,"passed_time":5.774470561,"remaining_time":16.26549341},
{"learn":[1.066102551],"iteration":262,"passed_time":5.79168455,"remaining_time":16.22992971},
{"learn":[1.066044553],"iteration":263,"passed_time":5.809769015,"remaining_time":16.1969318},
{"learn":[1.065908234],"iteration":264,"passed_time":5.83210678,"remaining_time":16.17584333},
{"learn":[1.065776873],"iteration":265,"passed_time":5.851808076,"remaining_time":16.1474704},
{"learn":[1.065659394],"iteration":266,"passed_time":5.870131749,"remaining_time":16.11538042},
{"learn":[1.065549356],"iteration":267,"passed_time":5.88932847,"remaining_time":16.08577776},
{"learn":[1.065518745],"iteration":268,"passed_time":5.909575888,"remaining_time":16.05910771},
{"learn":[1.065389097],"iteration":269,"passed_time":5.931082614,"remaining_time":16.03589003},
{"learn":[1.065317768],"iteration":270,"passed_time":5.950999379,"remaining_time":16.00840792},
{"learn":[1.065169641],"iteration":271,"passed_time":5.970548782,"remaining_time":15.97999821},
{"learn":[1.065051266],"iteration":272,"passed_time":5.992251199,"remaining_time":15.95738689},
{"learn":[1.064899816],"iteration":273,"passed_time":6.015591574,"remaining_time":15.9391222},
{"learn":[1.064798525],"iteration":274,"passed_time":6.034639682,"remaining_time":15.90950462},
{"learn":[1.064714714],"iteration":275,"passed_time":6.055359327,"remaining_time":15.88434838},
{"learn":[1.064638618],"iteration":276,"passed_time":6.075878272,"remaining_time":15.85870033},
{"learn":[1.064515196],"iteration":277,"passed_time":6.100600249,"remaining_time":15.84400496},
{"learn":[1.064365723],"iteration":278,"passed_time":6.138833528,"remaining_time":15.86415403},
{"learn":[1.064217821],"iteration":279,"passed_time":6.161252929,"remaining_time":15.84322182},
{"learn":[1.064144662],"iteration":280,"passed_time":6.178867958,"remaining_time":15.80998598},
{"learn":[1.064075949],"iteration":281,"passed_time":6.198995412,"remaining_time":15.78325782},
{"learn":[1.063978175],"iteration":282,"passed_time":6.219498908,"remaining_time":15.75752903},
{"learn":[1.063840067],"iteration":283,"passed_time":6.238760765,"remaining_time":15.72870672},
{"learn":[1.063789832],"iteration":284,"passed_time":6.256867979,"remaining_time":15.69705475},
{"learn":[1.063719423],"iteration":285,"passed_time":6.276948456,"remaining_time":15.67042377},
{"learn":[1.06363314],"iteration":286,"passed_time":6.297669261,"remaining_time":15.64542921},
{"learn":[1.063607214],"iteration":287,"passed_time":6.318062262,"remaining_time":15.61965393},
{"learn":[1.063517074],"iteration":288,"passed_time":6.337293401,"remaining_time":15.59105747},
{"learn":[1.063396794],"iteration":289,"passed_time":6.356583687,"remaining_time":15.56267041},
{"learn":[1.063313857],"iteration":290,"passed_time":6.375774817,"remaining_time":15.53410428},
{"learn":[1.063167494],"iteration":291,"passed_time":6.406586953,"remaining_time":15.53377932},
{"learn":[1.063016602],"iteration":292,"passed_time":6.427169615,"remaining_time":15.50856286},
{"learn":[1.062916964],"iteration":293,"passed_time":6.44748959,"remaining_time":15.48274711},
{"learn":[1.062845565],"iteration":294,"passed_time":6.463387974,"remaining_time":15.44640177},
{"learn":[1.062679742],"iteration":295,"passed_time":6.486068692,"remaining_time":15.42632554},
{"learn":[1.062571745],"iteration":296,"passed_time":6.507008766,"remaining_time":15.40211166},
{"learn":[1.062526332],"iteration":297,"passed_time":6.528715202,"remaining_time":15.37972507},
{"learn":[1.062340858],"iteration":298,"passed_time":6.550410669,"remaining_time":15.35731732},
{"learn":[1.062231772],"iteration":299,"passed_time":6.576360635,"remaining_time":15.34484148},
{"learn":[1.062108982],"iteration":300,"passed_time":6.59768527,"remaining_time":15.3215349},
{"learn":[1.061981126],"iteration":301,"passed_time":6.620853014,"remaining_time":15.30250134},
{"learn":[1.061912407],"iteration":302,"passed_time":6.637990917,"remaining_time":15.26956986},
{"learn":[1.06179067],"iteration":303,"passed_time":6.658401057,"remaining_time":15.244234},
{"learn":[1.061663808],"iteration":304,"passed_time":6.678440946,"remaining_time":15.21808675},
{"learn":[1.061600674],"iteration":305,"passed_time":6.697516512,"remaining_time":15.18979235},
{"learn":[1.061566396],"iteration":306,"passed_time":6.714987608,"remaining_time":15.1579362},
{"learn":[1.06148327],"iteration":307,"passed_time":6.751314521,"remaining_time":15.16853782},
{"learn":[1.061374935],"iteration":308,"passed_time":6.772781289,"remaining_time":15.14560476},
{"learn":[1.061332823],"iteration":309,"passed_time":6.790301143,"remaining_time":15.11389609},
{"learn":[1.061186254],"iteration":310,"passed_time":6.815368313,"remaining_time":15.09899925},
{"learn":[1.061037981],"iteration":311,"passed_time":6.837732706,"remaining_time":15.07807725},
{"learn":[1.060940403],"iteration":312,"passed_time":6.856878779,"remaining_time":15.05008218},
{"learn":[1.060839173],"iteration":313,"passed_time":6.876219892,"remaining_time":15.02256957},
{"learn":[1.060735813],"iteration":314,"passed_time":6.895749506,"remaining_time":14.99551877},
{"learn":[1.060671573],"iteration":315,"passed_time":6.914447042,"remaining_time":14.96671448},
{"learn":[1.060571522],"iteration":316,"passed_time":6.935932759,"remaining_time":14.94398131},
{"learn":[1.060464988],"iteration":317,"passed_time":6.95672563,"remaining_time":14.91977006},
{"learn":[1.060378772],"iteration":318,"passed_time":6.974964658,"remaining_time":14.89012831},
{"learn":[1.060337509],"iteration":319,"passed_time":6.992353448,"remaining_time":14.85875108},
{"learn":[1.060241273],"iteration":320,"passed_time":7.016123052,"remaining_time":14.84095811},
{"learn":[1.060106628],"iteration":321,"passed_time":7.03719437,"remaining_time":14.81744653},
{"learn":[1.060001479],"iteration":322,"passed_time":7.057325694,"remaining_time":14.79197986},
{"learn":[1.05993237],"iteration":323,"passed_time":7.075493545,"remaining_time":14.7624495},
{"learn":[1.059867916],"iteration":324,"passed_time":7.094078026,"remaining_time":14.73385436},
{"learn":[1.059752628],"iteration":325,"passed_time":7.115441369,"remaining_time":14.7110659},
{"learn":[1.059711113],"iteration":326,"passed_time":7.133902666,"remaining_time":14.68231344},
{"learn":[1.05956946],"iteration":327,"passed_time":7.153938875,"remaining_time":14.65685038},
{"learn":[1.059469533],"iteration":328,"passed_time":7.174969315,"remaining_time":14.63344806},
{"learn":[1.05939676],"iteration":329,"passed_time":7.193143216,"remaining_time":14.60426047},
{"learn":[1.059321797],"iteration":330,"passed_time":7.214603234,"remaining_time":14.58178116},
{"learn":[1.059210534],"iteration":331,"passed_time":7.233356316,"remaining_time":14.5538615},
{"learn":[1.059067051],"iteration":332,"passed_time":7.253004315,"remaining_time":14.52778942},
{"learn":[1.05894216],"iteration":333,"passed_time":7.272720339,"remaining_time":14.50189145},
{"learn":[1.058902471],"iteration":334,"passed_time":7.290226603,"remaining_time":14.47164385},
{"learn":[1.058818915],"iteration":335,"passed_time":7.309223304,"remaining_time":14.44441748},
{"learn":[1.058733882],"iteration":336,"passed_time":7.327743788,"remaining_time":14.41630306},
{"learn":[1.058640504],"iteration":337,"passed_time":7.358288327,"remaining_time":14.41179548},
{"learn":[1.058537026],"iteration":338,"passed_time":7.385156248,"remaining_time":14.39996543},
{"learn":[1.058404315],"iteration":339,"passed_time":7.411983971,"remaining_time":14.38796888},
{"learn":[1.058319153],"iteration":340,"passed_time":7.432993091,"remaining_time":14.36464061},
{"learn":[1.058257727],"iteration":341,"passed_time":7.450293775,"remaining_time":14.33419095},
{"learn":[1.058143192],"iteration":342,"passed_time":7.471246249,"remaining_time":14.31081279},
{"learn":[1.058007111],"iteration":343,"passed_time":7.492758145,"remaining_time":14.28851553},
{"learn":[1.057941923],"iteration":344,"passed_time":7.516755458,"remaining_time":14.27094152},
{"learn":[1.057897812],"iteration":345,"passed_time":7.534353447,"remaining_time":14.24123455},
{"learn":[1.057816077],"iteration":346,"passed_time":7.553355947,"remaining_time":14.21424044},
{"learn":[1.05768745],"iteration":347,"passed_time":7.575074453,"remaining_time":14.19238087},
{"learn":[1.057617591],"iteration":348,"passed_time":7.60545142,"remaining_time":14.18667299},
{"learn":[1.057492106],"iteration":349,"passed_time":7.628801015,"remaining_time":14.16777331},
{"learn":[1.057388716],"iteration":350,"passed_time":7.650119221,"remaining_time":14.14509223},
{"learn":[1.057253518],"iteration":351,"passed_time":7.672882165,"remaining_time":14.12507853},
{"learn":[1.05712768],"iteration":352,"passed_time":7.693133473,"remaining_time":14.10044577},
{"learn":[1.057055257],"iteration":353,"passed_time":7.714268708,"remaining_time":14.07745081},
{"learn":[1.056955751],"iteration":354,"passed_time":7.734699267,"remaining_time":14.05318599},
{"learn":[1.056865729],"iteration":355,"passed_time":7.752200851,"remaining_time":14.02364424},
{"learn":[1.056803768],"iteration":356,"passed_time":7.770361473,"remaining_time":13.99535694},
{"learn":[1.056766947],"iteration":357,"passed_time":7.787727884,"remaining_time":13.96570196},
{"learn":[1.056680045],"iteration":358,"passed_time":7.80984013,"remaining_time":13.9445892},
{"learn":[1.056610192],"iteration":359,"passed_time":7.827398232,"remaining_time":13.91537463},
{"learn":[1.056518286],"iteration":360,"passed_time":7.848030611,"remaining_time":13.89166637},
{"learn":[1.05637226],"iteration":361,"passed_time":7.872663513,"remaining_time":13.87502575},
{"learn":[1.056289395],"iteration":362,"passed_time":7.893111721,"remaining_time":13.8509977},
{"learn":[1.056221298],"iteration":363,"passed_time":7.912027065,"remaining_time":13.82431103},
{"learn":[1.056167129],"iteration":364,"passed_time":7.928787796,"remaining_time":13.7939185},
{"learn":[1.056055788],"iteration":365,"passed_time":7.952131322,"remaining_time":13.77500344},
{"learn":[1.055931441],"iteration":366,"passed_time":7.972139072,"remaining_time":13.75031072},
{"learn":[1.055818591],"iteration":367,"passed_time":7.99301191,"remaining_time":13.72712915},
{"learn":[1.055691983],"iteration":368,"passed_time":8.020209324,"remaining_time":13.71477529},
{"learn":[1.055576226],"iteration":369,"passed_time":8.04090769,"remaining_time":13.69127526},
{"learn":[1.055468566],"iteration":370,"passed_time":8.060493801,"remaining_time":13.66590459},
{"learn":[1.055357576],"iteration":371,"passed_time":8.082733031,"remaining_time":13.64504393},
{"learn":[1.055253363],"iteration":372,"passed_time":8.103047577,"remaining_time":13.62094056},
{"learn":[1.055199988],"iteration":373,"passed_time":8.121830827,"remaining_time":13.59429438},
{"learn":[1.055130139],"iteration":374,"passed_time":8.139241676,"remaining_time":13.56540279},
{"learn":[1.055033882],"iteration":375,"passed_time":8.159158491,"remaining_time":13.54073111},
{"learn":[1.054954295],"iteration":376,"passed_time":8.179702005,"remaining_time":13.51712029},
{"learn":[1.0548371],"iteration":377,"passed_time":8.200276787,"remaining_time":13.49357715},
{"learn":[1.054728855],"iteration":378,"passed_time":8.220186962,"remaining_time":13.4689607},
{"learn":[1.054678701],"iteration":379,"passed_time":8.238693357,"remaining_time":13.44207863},
{"learn":[1.054597164],"iteration":380,"passed_time":8.258141545,"remaining_time":13.41677065},
{"learn":[1.054528273],"iteration":381,"passed_time":8.277581103,"remaining_time":13.39147938},
{"learn":[1.054396817],"iteration":382,"passed_time":8.299655551,"remaining_time":13.37046338},
{"learn":[1.054317527],"iteration":383,"passed_time":8.321118629,"remaining_time":13.34846113},
{"learn":[1.054243999],"iteration":384,"passed_time":8.342354449,"remaining_time":13.32609867},
{"learn":[1.054203009],"iteration":385,"passed_time":8.368226639,"remaining_time":13.31111699},
{"learn":[1.05410218],"iteration":386,"passed_time":8.38741942,"remaining_time":13.28549898},
{"learn":[1.054078265],"iteration":387,"passed_time":8.407128505,"remaining_time":13.26072847},
{"learn":[1.053987229],"iteration":388,"passed_time":8.426863539,"remaining_time":13.23602474},
{"learn":[1.053831462],"iteration":389,"passed_time":8.450862622,"remaining_time":13.2180159},
{"learn":[1.053762974],"iteration":390,"passed_time":8.46868365,"remaining_time":13.19035382},
{"learn":[1.05361989],"iteration":391,"passed_time":8.488152387,"remaining_time":13.16529758},
{"learn":[1.053503471],"iteration":392,"passed_time":8.509704341,"remaining_time":13.14348737},
{"learn":[1.053362263],"iteration":393,"passed_time":8.530965539,"remaining_time":13.12123126},
{"learn":[1.05326279],"iteration":394,"passed_time":8.555232859,"remaining_time":13.10358451},
{"learn":[1.05317715],"iteration":395,"passed_time":8.575141104,"remaining_time":13.07925562},
{"learn":[1.053097417],"iteration":396,"passed_time":8.596366404,"remaining_time":13.05694948},
{"learn":[1.053056062],"iteration":397,"passed_time":8.621271962,"remaining_time":13.04021538},
{"learn":[1.052974298],"iteration":398,"passed_time":8.645152001,"remaining_time":13.02189562},
{"learn":[1.052815628],"iteration":399,"passed_time":8.667384171,"remaining_time":13.00107626},
{"learn":[1.052739086],"iteration":400,"passed_time":8.685146543,"remaining_time":12.97357301},
{"learn":[1.052618545],"iteration":401,"passed_time":8.705980532,"remaining_time":12.95068746},
{"learn":[1.052565812],"iteration":402,"passed_time":8.726222261,"remaining_time":12.92693471},
{"learn":[1.052490572],"iteration":403,"passed_time":8.745067329,"remaining_time":12.90113893},
{"learn":[1.052430667],"iteration":404,"passed_time":8.765974574,"remaining_time":12.87840709},
{"learn":[1.052249558],"iteration":405,"passed_time":8.787925908,"remaining_time":12.8572118},
{"learn":[1.052135424],"iteration":406,"passed_time":8.809024865,"remaining_time":12.83477087},
{"learn":[1.052047516],"iteration":407,"passed_time":8.833648707,"remaining_time":12.81745106},
{"learn":[1.051930132],"iteration":408,"passed_time":8.857586313,"remaining_time":12.79910394},
{"learn":[1.051879739],"iteration":409,"passed_time":8.875103166,"remaining_time":12.77148992},
{"learn":[1.051819104],"iteration":410,"passed_time":8.896172994,"remaining_time":12.74901677},
{"learn":[1.051713042],"iteration":411,"passed_time":8.915844221,"remaining_time":12.72455437},
{"learn":[1.051613042],"iteration":412,"passed_time":8.935203283,"remaining_time":12.69967149},
{"learn":[1.051544353],"iteration":413,"passed_time":8.954641522,"remaining_time":12.67492737},
{"learn":[1.051513396],"iteration":414,"passed_time":8.974342717,"remaining_time":12.65057949},
{"learn":[1.051400951],"iteration":415,"passed_time":8.996345409,"remaining_time":12.6294849},
{"learn":[1.051322379],"iteration":416,"passed_time":9.019282174,"remaining_time":12.60969186},
{"learn":[1.051229174],"iteration":417,"passed_time":9.041167212,"remaining_time":12.58841942},
{"learn":[1.051153428],"iteration":418,"passed_time":9.063988343,"remaining_time":12.56844207},
{"learn":[1.051118148],"iteration":419,"passed_time":9.084757525,"remaining_time":12.54561754},
{"learn":[1.051067848],"iteration":420,"passed_time":9.105127788,"remaining_time":12.52225413},
{"learn":[1.050943204],"iteration":421,"passed_time":9.124591805,"remaining_time":12.49766366},
{"learn":[1.050825318],"iteration":422,"passed_time":9.14551284,"remaining_time":12.47508489},
{"learn":[1.050730384],"iteration":423,"passed_time":9.166673333,"remaining_time":12.45283925},
{"learn":[1.050657571],"iteration":424,"passed_time":9.187549151,"remaining_time":12.43021356},
{"learn":[1.050562973],"iteration":425,"passed_time":9.209350532,"remaining_time":12.40884321},
{"learn":[1.050442783],"iteration":426,"passed_time":9.227973521,"remaining_time":12.38320569},
{"learn":[1.050394606],"iteration":427,"passed_time":9.24801468,"remaining_time":12.35949625},
{"learn":[1.050276791],"iteration":428,"passed_time":9.267666208,"remaining_time":12.33528533},
{"learn":[1.05020122],"iteration":429,"passed_time":9.287124065,"remaining_time":12.31083888},
{"learn":[1.050095579],"iteration":430,"passed_time":9.313357458,"remaining_time":12.29536054},
{"learn":[1.049976486],"iteration":431,"passed_time":9.336241676,"remaining_time":12.27542887},
{"learn":[1.049836864],"iteration":432,"passed_time":9.366229812,"remaining_time":12.26478592},
{"learn":[1.049771892],"iteration":433,"passed_time":9.386741758,"remaining_time":12.24169547},
{"learn":[1.049666218],"iteration":434,"passed_time":9.411830027,"remaining_time":12.22456084},
{"learn":[1.049587983],"iteration":435,"passed_time":9.43158231,"remaining_time":12.20048721},
{"learn":[1.049476273],"iteration":436,"passed_time":9.451107494,"remaining_time":12.17614078},
{"learn":[1.04935101],"iteration":437,"passed_time":9.472518025,"remaining_time":12.15423546},
{"learn":[1.049252495],"iteration":438,"passed_time":9.496108668,"remaining_time":12.13511837},
{"learn":[1.049152109],"iteration":439,"passed_time":9.517659482,"remaining_time":12.11338479},
{"learn":[1.049060315],"iteration":440,"passed_time":9.541404957,"remaining_time":12.09443395},
{"learn":[1.048993565],"iteration":441,"passed_time":9.56256376,"remaining_time":12.07219588},
{"learn":[1.048889107],"iteration":442,"passed_time":9.584535114,"remaining_time":12.05098433},
{"learn":[1.04879308],"iteration":443,"passed_time":9.603044618,"remaining_time":12.02543425},
{"learn":[1.048751752],"iteration":444,"passed_time":9.623762633,"remaining_time":12.00267025},
{"learn":[1.04861859],"iteration":445,"passed_time":9.649140348,"remaining_time":11.98570348},
{"learn":[1.048523064],"iteration":446,"passed_time":9.67032439,"remaining_time":11.96351093},
{"learn":[1.048423484],"iteration":447,"passed_time":9.692302623,"remaining_time":11.94230145},
{"learn":[1.04831812],"iteration":448,"passed_time":9.712929052,"remaining_time":11.91942964},
{"learn":[1.048194305],"iteration":449,"passed_time":9.733152702,"remaining_time":11.89607552},
{"learn":[1.048066326],"iteration":450,"passed_time":9.751928313,"remaining_time":11.8709726},
{"learn":[1.047954977],"iteration":451,"passed_time":9.775361054,"remaining_time":11.85154393},
{"learn":[1.047817356],"iteration":452,"passed_time":9.797254991,"remaining_time":11.83023947},
{"learn":[1.047740131],"iteration":453,"passed_time":9.816063731,"remaining_time":11.80522202},
{"learn":[1.047673919],"iteration":454,"passed_time":9.832755215,"remaining_time":11.77769581},
{"learn":[1.047514572],"iteration":455,"passed_time":9.855556617,"remaining_time":11.75750614},
{"learn":[1.04746637],"iteration":456,"passed_time":9.875222665,"remaining_time":11.73357966},
{"learn":[1.047416156],"iteration":457,"passed_time":9.895154309,"remaining_time":11.7099861},
{"learn":[1.047334346],"iteration":458,"passed_time":9.914724671,"remaining_time":11.68598267},
{"learn":[1.047279837],"iteration":459,"passed_time":9.937141132,"remaining_time":11.66533959},
{"learn":[1.047227696],"iteration":460,"passed_time":9.955761061,"remaining_time":11.64024992},
{"learn":[1.04711512],"iteration":461,"passed_time":9.977505155,"remaining_time":11.61882635},
{"learn":[1.047045453],"iteration":462,"passed_time":9.998527475,"remaining_time":11.59656426},
{"learn":[1.046976476],"iteration":463,"passed_time":10.01963081,"remaining_time":11.57440111},
{"learn":[1.046930375],"iteration":464,"passed_time":10.04052604,"remaining_time":11.55200308},
{"learn":[1.046846852],"iteration":465,"passed_time":10.05956393,"remaining_time":11.52748313},
{"learn":[1.046733114],"iteration":466,"passed_time":10.08085292,"remaining_time":11.50555591},
{"learn":[1.046647243],"iteration":467,"passed_time":10.10264141,"remaining_time":11.4841992},
{"learn":[1.046516031],"iteration":468,"passed_time":10.12469205,"remaining_time":11.46313749},
{"learn":[1.046440398],"iteration":469,"passed_time":10.14201523,"remaining_time":11.43674058},
{"learn":[1.046333947],"iteration":470,"passed_time":10.16139253,"remaining_time":11.41268927},
{"learn":[1.046219572],"iteration":471,"passed_time":10.17969476,"remaining_time":11.38745516},
{"learn":[1.046100345],"iteration":472,"passed_time":10.20061311,"remaining_time":11.36516513},
{"learn":[1.046049973],"iteration":473,"passed_time":10.21991981,"remaining_time":11.34109245},
{"learn":[1.045928133],"iteration":474,"passed_time":10.24036498,"remaining_time":11.31829814},
{"learn":[1.045836229],"iteration":475,"passed_time":10.26153945,"remaining_time":11.29631653},
{"learn":[1.045765966],"iteration":476,"passed_time":10.28082131,"remaining_time":11.2722632},
{"learn":[1.045708995],"iteration":477,"passed_time":10.3001642,"remaining_time":11.24829647},
{"learn":[1.045650314],"iteration":478,"passed_time":10.31827161,"remaining_time":11.22300524},
{"learn":[1.045512041],"iteration":479,"passed_time":10.34891674,"remaining_time":11.21132647},
{"learn":[1.045429751],"iteration":480,"passed_time":10.37416534,"remaining_time":11.19374597},
{"learn":[1.04534651],"iteration":481,"passed_time":10.40016353,"remaining_time":11.17693923},
{"learn":[1.045273391],"iteration":482,"passed_time":10.42245633,"remaining_time":11.1561282},
{"learn":[1.045159135],"iteration":483,"passed_time":10.44667262,"remaining_time":11.13736172},
{"learn":[1.04506287],"iteration":484,"passed_time":10.46944713,"remaining_time":11.1170418},
{"learn":[1.04496931],"iteration":485,"passed_time":10.4930637,"remaining_time":11.09760235},
{"learn":[1.044930178],"iteration":486,"passed_time":10.51367866,"remaining_time":11.07498389},
{"learn":[1.044867278],"iteration":487,"passed_time":10.53716356,"remaining_time":11.05538472},
{"learn":[1.044725393],"iteration":488,"passed_time":10.56158954,"remaining_time":11.03675308},
{"learn":[1.04468081],"iteration":489,"passed_time":10.58372245,"remaining_time":11.01571112},
{"learn":[1.044614342],"iteration":490,"passed_time":10.60472793,"remaining_time":10.99349596},
{"learn":[1.04454538],"iteration":491,"passed_time":10.62872177,"remaining_time":10.97437126},
{"learn":[1.044469294],"iteration":492,"passed_time":10.6521302,"remaining_time":10.95462477},
{"learn":[1.044410656],"iteration":493,"passed_time":10.67477185,"remaining_time":10.93407805},
{"learn":[1.0442902],"iteration":494,"passed_time":10.69671091,"remaining_time":10.91280608},
{"learn":[1.044232204],"iteration":495,"passed_time":10.71758091,"remaining_time":10.89044511},
{"learn":[1.04412055],"iteration":496,"passed_time":10.74079658,"remaining_time":10.87046414},
{"learn":[1.044062242],"iteration":497,"passed_time":10.75992028,"remaining_time":10.84634534},
{"learn":[1.04400685],"iteration":498,"passed_time":10.7773069,"remaining_time":10.82050252},
{"learn":[1.04389841],"iteration":499,"passed_time":10.79773492,"remaining_time":10.79773492},
{"learn":[1.043784811],"iteration":500,"passed_time":10.81649893,"remaining_time":10.7733193},
{"learn":[1.04372603],"iteration":501,"passed_time":10.83710731,"remaining_time":10.75075586},
{"learn":[1.043650958],"iteration":502,"passed_time":10.85455214,"remaining_time":10.72507438},
{"learn":[1.043607048],"iteration":503,"passed_time":10.87314775,"remaining_time":10.7005581},
{"learn":[1.04356639],"iteration":504,"passed_time":10.89207224,"remaining_time":10.67638764},
{"learn":[1.043527475],"iteration":505,"passed_time":10.90895683,"remaining_time":10.65024639},
{"learn":[1.043470384],"iteration":506,"passed_time":10.92776604,"remaining_time":10.62601313},
{"learn":[1.043436047],"iteration":507,"passed_time":10.9472405,"remaining_time":10.60244552},
{"learn":[1.043356667],"iteration":508,"passed_time":10.96785662,"remaining_time":10.57999528},
{"learn":[1.043258353],"iteration":509,"passed_time":10.99064681,"remaining_time":10.55964105},
{"learn":[1.043200642],"iteration":510,"passed_time":11.00745481,"remaining_time":10.53355264},
{"learn":[1.043104986],"iteration":511,"passed_time":11.02823656,"remaining_time":10.51128797},
{"learn":[1.042965616],"iteration":512,"passed_time":11.04916774,"remaining_time":10.48917094},
{"learn":[1.042889272],"iteration":513,"passed_time":11.06968562,"remaining_time":10.46666773},
{"learn":[1.042800364],"iteration":514,"passed_time":11.09065053,"remaining_time":10.44459322},
{"learn":[1.042703359],"iteration":515,"passed_time":11.11137459,"remaining_time":10.42229709},
{"learn":[1.042600998],"iteration":516,"passed_time":11.13334343,"remaining_time":10.40116997},
{"learn":[1.042514826],"iteration":517,"passed_time":11.15617856,"remaining_time":10.38084569},
{"learn":[1.042368693],"iteration":518,"passed_time":11.17808674,"remaining_time":10.35965264},
{"learn":[1.042272992],"iteration":519,"passed_time":11.19903953,"remaining_time":10.33757495},
{"learn":[1.042159954],"iteration":520,"passed_time":11.21907938,"remaining_time":10.31466223},
{"learn":[1.042112528],"iteration":521,"passed_time":11.23848325,"remaining_time":10.29117815},
{"learn":[1.042025483],"iteration":522,"passed_time":11.26062746,"remaining_time":10.27020899},
{"learn":[1.041923443],"iteration":523,"passed_time":11.28592409,"remaining_time":10.25209899},
{"learn":[1.041838343],"iteration":524,"passed_time":11.30771443,"remaining_time":10.23078924},
{"learn":[1.041769075],"iteration":525,"passed_time":11.33211954,"remaining_time":10.21183396},
{"learn":[1.041614249],"iteration":526,"passed_time":11.35210281,"remaining_time":10.18888924},
{"learn":[1.041491596],"iteration":527,"passed_time":11.37409804,"remaining_time":10.16775431},
{"learn":[1.041423903],"iteration":528,"passed_time":11.39530987,"remaining_time":10.14591862},
{"learn":[1.041392565],"iteration":529,"passed_time":11.41477061,"remaining_time":10.12253243},
{"learn":[1.04135261],"iteration":530,"passed_time":11.43538873,"remaining_time":10.10018327},
{"learn":[1.041293228],"iteration":531,"passed_time":11.45576495,"remaining_time":10.07762781},
{"learn":[1.041247437],"iteration":532,"passed_time":11.4741243,"remaining_time":10.05331341},
{"learn":[1.041222072],"iteration":533,"passed_time":11.49455132,"remaining_time":10.03082569},
{"learn":[1.041189056],"iteration":534,"passed_time":11.51456433,"remaining_time":10.00798582},
{"learn":[1.041073543],"iteration":535,"passed_time":11.53533157,"remaining_time":9.985809415},
{"learn":[1.040982642],"iteration":536,"passed_time":11.55790095,"remaining_time":9.965192066},
{"learn":[1.040910849],"iteration":537,"passed_time":11.5822846,"remaining_time":9.94612544},
{"learn":[1.040851742],"iteration":538,"passed_time":11.59958083,"remaining_time":9.920977294},
{"learn":[1.040748388],"iteration":539,"passed_time":11.62034469,"remaining_time":9.898812144},
{"learn":[1.040720844],"iteration":540,"passed_time":11.63844717,"remaining_time":9.874394175},
{"learn":[1.040685992],"iteration":541,"passed_time":11.65640589,"remaining_time":9.849878037},
{"learn":[1.040604446],"iteration":542,"passed_time":11.68487312,"remaining_time":9.834230231},
{"learn":[1.040499541],"iteration":543,"passed_time":11.70263091,"remaining_time":9.809558263},
{"learn":[1.040405094],"iteration":544,"passed_time":11.72303751,"remaining_time":9.78712306},
{"learn":[1.040304735],"iteration":545,"passed_time":11.74328651,"remaining_time":9.76456424},
{"learn":[1.040205262],"iteration":546,"passed_time":11.76345177,"remaining_time":9.74194452},
{"learn":[1.040134964],"iteration":547,"passed_time":11.78634829,"remaining_time":9.721586545},
{"learn":[1.040055991],"iteration":548,"passed_time":11.80584305,"remaining_time":9.698424805},
{"learn":[1.039936911],"iteration":549,"passed_time":11.82617288,"remaining_time":9.675959628},
{"learn":[1.039816564],"iteration":550,"passed_time":11.84603731,"remaining_time":9.653122959},
{"learn":[1.039747204],"iteration":551,"passed_time":11.86664142,"remaining_time":9.630897382},
{"learn":[1.039656226],"iteration":552,"passed_time":11.88876847,"remaining_time":9.609908693},
{"learn":[1.039606252],"iteration":553,"passed_time":11.9093523,"remaining_time":9.587673516},
{"learn":[1.039494692],"iteration":554,"passed_time":11.92876254,"remaining_time":9.564503302},
{"learn":[1.039449572],"iteration":555,"passed_time":11.94630307,"remaining_time":9.539853528},
{"learn":[1.039333248],"iteration":556,"passed_time":11.96535728,"remaining_time":9.516433172},
{"learn":[1.039239207],"iteration":557,"passed_time":11.98925867,"remaining_time":9.49686798},
{"learn":[1.039208832],"iteration":558,"passed_time":12.00689259,"remaining_time":9.472342812},
{"learn":[1.039158286],"iteration":559,"passed_time":12.0245031,"remaining_time":9.447823863},
{"learn":[1.039074148],"iteration":560,"passed_time":12.04383643,"remaining_time":9.424677707},
{"learn":[1.039020569],"iteration":561,"passed_time":12.06669472,"remaining_time":9.404292328},
{"learn":[1.038920222],"iteration":562,"passed_time":12.08821801,"remaining_time":9.382861934},
{"learn":[1.038886642],"iteration":563,"passed_time":12.1053735,"remaining_time":9.35805469},
{"learn":[1.038851045],"iteration":564,"passed_time":12.12625436,"remaining_time":9.336142734},
{"learn":[1.038802938],"iteration":565,"passed_time":12.14413219,"remaining_time":9.311931751},
{"learn":[1.038757438],"iteration":566,"passed_time":12.16432753,"remaining_time":9.289512913},
{"learn":[1.038692405],"iteration":567,"passed_time":12.18353362,"remaining_time":9.266349515},
{"learn":[1.03861507],"iteration":568,"passed_time":12.20366085,"remaining_time":9.243897759},
{"learn":[1.03855118],"iteration":569,"passed_time":12.22368989,"remaining_time":9.221380089},
{"learn":[1.038464545],"iteration":570,"passed_time":12.2461131,"remaining_time":9.20066991},
{"learn":[1.038326556],"iteration":571,"passed_time":12.2667229,"remaining_time":9.178596853},
{"learn":[1.038235891],"iteration":572,"passed_time":12.28795923,"remaining_time":9.156995794},
{"learn":[1.038178307],"iteration":573,"passed_time":12.30774525,"remaining_time":9.134319644},
{"learn":[1.038110658],"iteration":574,"passed_time":12.33081266,"remaining_time":9.11407892},
{"learn":[1.037981752],"iteration":575,"passed_time":12.35005937,"remaining_time":9.091015929},
{"learn":[1.037917911],"iteration":576,"passed_time":12.37343349,"remaining_time":9.070991968},
{"learn":[1.037852419],"iteration":577,"passed_time":12.39302956,"remaining_time":9.048198052},
{"learn":[1.037742127],"iteration":578,"passed_time":12.41428167,"remaining_time":9.026619313},
{"learn":[1.037666086],"iteration":579,"passed_time":12.43413274,"remaining_time":9.004027154},
{"learn":[1.037585621],"iteration":580,"passed_time":12.45450953,"remaining_time":8.981823567},
{"learn":[1.037555958],"iteration":581,"passed_time":12.47654986,"remaining_time":8.960821032},
{"learn":[1.037467831],"iteration":582,"passed_time":12.50072848,"remaining_time":8.941344386},
{"learn":[1.03734677],"iteration":583,"passed_time":12.52452686,"remaining_time":8.92158078},
{"learn":[1.037243281],"iteration":584,"passed_time":12.54641859,"remaining_time":8.900450796},
{"learn":[1.03715787],"iteration":585,"passed_time":12.56513363,"remaining_time":8.877073927},
{"learn":[1.037097837],"iteration":586,"passed_time":12.5872351,"remaining_time":8.856095566},
{"learn":[1.037021053],"iteration":587,"passed_time":12.60761122,"remaining_time":8.833904464},
{"learn":[1.036903368],"iteration":588,"passed_time":12.63028823,"remaining_time":8.813325066},
{"learn":[1.036816891],"iteration":589,"passed_time":12.65210958,"remaining_time":8.792143948},
{"learn":[1.036770175],"iteration":590,"passed_time":12.67158503,"remaining_time":8.769337187},
{"learn":[1.036663319],"iteration":591,"passed_time":12.69743618,"remaining_time":8.750935747},
{"learn":[1.036585305],"iteration":592,"passed_time":12.72444904,"remaining_time":8.733306505},
{"learn":[1.036497535],"iteration":593,"passed_time":12.74568905,"remaining_time":8.711699926},
{"learn":[1.036462045],"iteration":594,"passed_time":12.76521634,"remaining_time":8.688928768},
{"learn":[1.036380209],"iteration":595,"passed_time":12.78465446,"remaining_time":8.666108055},
{"learn":[1.036285155],"iteration":596,"passed_time":12.80261593,"remaining_time":8.642301875},
{"learn":[1.036191638],"iteration":597,"passed_time":12.82190039,"remaining_time":8.619404613},
{"learn":[1.036058599],"iteration":598,"passed_time":12.84185026,"remaining_time":8.596964864},
{"learn":[1.03600488],"iteration":599,"passed_time":12.86104712,"remaining_time":8.574031412},
{"learn":[1.035872354],"iteration":600,"passed_time":12.88544044,"remaining_time":8.554560293},
{"learn":[1.035793768],"iteration":601,"passed_time":12.90488758,"remaining_time":8.531802752},
{"learn":[1.035748984],"iteration":602,"passed_time":12.92240788,"remaining_time":8.507787611},
{"learn":[1.035597526],"iteration":603,"passed_time":12.94365421,"remaining_time":8.486236868},
{"learn":[1.035483007],"iteration":604,"passed_time":12.96377424,"remaining_time":8.463951775},
{"learn":[1.035366752],"iteration":605,"passed_time":12.98604035,"remaining_time":8.443069136},
{"learn":[1.03534688],"iteration":606,"passed_time":13.0058504,"remaining_time":8.420591772},
{"learn":[1.03529409],"iteration":607,"passed_time":13.0262477,"remaining_time":8.398501804},
{"learn":[1.035250568],"iteration":608,"passed_time":13.04777231,"remaining_time":8.377141172},
{"learn":[1.035135263],"iteration":609,"passed_time":13.07857999,"remaining_time":8.361715074},
{"learn":[1.035102663],"iteration":610,"passed_time":13.10520408,"remaining_time":8.343575102},
{"learn":[1.035039649],"iteration":611,"passed_time":13.12891586,"remaining_time":8.323561034},
{"learn":[1.034868728],"iteration":612,"passed_time":13.15187234,"remaining_time":8.303058069},
{"learn":[1.034839175],"iteration":613,"passed_time":13.17352152,"remaining_time":8.281725256},
{"learn":[1.034742266],"iteration":614,"passed_time":13.19306129,"remaining_time":8.259070886},
{"learn":[1.034666928],"iteration":615,"passed_time":13.21061136,"remaining_time":8.2351863},
{"learn":[1.034538534],"iteration":616,"passed_time":13.23211282,"remaining_time":8.213775059},
{"learn":[1.034446104],"iteration":617,"passed_time":13.25710522,"remaining_time":8.194521348},
{"learn":[1.034401477],"iteration":618,"passed_time":13.27914582,"remaining_time":8.173432239},
{"learn":[1.034351239],"iteration":619,"passed_time":13.29771797,"remaining_time":8.150214239},
{"learn":[1.034248787],"iteration":620,"passed_time":13.32521244,"remaining_time":8.132456544},
{"learn":[1.034167864],"iteration":621,"passed_time":13.3456195,"remaining_time":8.110360403},
{"learn":[1.034105651],"iteration":622,"passed_time":13.36510183,"remaining_time":8.087710099},
{"learn":[1.03405099],"iteration":623,"passed_time":13.38410305,"remaining_time":8.06478004},
{"learn":[1.034017068],"iteration":624,"passed_time":13.40121135,"remaining_time":8.040726809},
{"learn":[1.033937946],"iteration":625,"passed_time":13.41993434,"remaining_time":8.017660454},
{"learn":[1.033846684],"iteration":626,"passed_time":13.44043629,"remaining_time":7.995666245},
{"learn":[1.033758576],"iteration":627,"passed_time":13.46107632,"remaining_time":7.973758583},
{"learn":[1.033654903],"iteration":628,"passed_time":13.4823181,"remaining_time":7.952209879},
{"learn":[1.033575458],"iteration":629,"passed_time":13.5048625,"remaining_time":7.931427183},
{"learn":[1.033502351],"iteration":630,"passed_time":13.52371145,"remaining_time":7.908477852},
{"learn":[1.033359086],"iteration":631,"passed_time":13.54452791,"remaining_time":7.886687137},
{"learn":[1.033230277],"iteration":632,"passed_time":13.56684881,"remaining_time":7.86577174},
{"learn":[1.033166966],"iteration":633,"passed_time":13.58761967,"remaining_time":7.843957095},
{"learn":[1.03305785],"iteration":634,"passed_time":13.60734635,"remaining_time":7.821545541},
{"learn":[1.033029899],"iteration":635,"passed_time":13.62423824,"remaining_time":7.797519997},
{"learn":[1.032970738],"iteration":636,"passed_time":13.64374823,"remaining_time":7.775008804},
{"learn":[1.032871247],"iteration":637,"passed_time":13.66866384,"remaining_time":7.755574153},
{"learn":[1.032796407],"iteration":638,"passed_time":13.69333329,"remaining_time":7.735983282},
{"learn":[1.03266305],"iteration":639,"passed_time":13.71807581,"remaining_time":7.716417646},
{"learn":[1.032610869],"iteration":640,"passed_time":13.73815414,"remaining_time":7.694223614},
{"learn":[1.032540045],"iteration":641,"passed_time":13.75690781,"remaining_time":7.671297504},
{"learn":[1.032447013],"iteration":642,"passed_time":13.7767476,"remaining_time":7.648987394},
{"learn":[1.032359942],"iteration":643,"passed_time":13.796815,"remaining_time":7.626810776},
{"learn":[1.032242375],"iteration":644,"passed_time":13.81705559,"remaining_time":7.604736022},
{"learn":[1.032183316],"iteration":645,"passed_time":13.83810732,"remaining_time":7.58311144},
{"learn":[1.032050186],"iteration":646,"passed_time":13.86011216,"remaining_time":7.562008643},
{"learn":[1.031942558],"iteration":647,"passed_time":13.88386665,"remaining_time":7.541853491},
{"learn":[1.031906792],"iteration":648,"passed_time":13.90068011,"remaining_time":7.517933312},
{"learn":[1.031833099],"iteration":649,"passed_time":13.92213155,"remaining_time":7.496532374},
{"learn":[1.031777666],"iteration":650,"passed_time":13.94203244,"remaining_time":7.474300031},
{"learn":[1.03173015],"iteration":651,"passed_time":13.95970347,"remaining_time":7.450884676},
{"learn":[1.03164897],"iteration":652,"passed_time":13.98078672,"remaining_time":7.42930014},
{"learn":[1.031577655],"iteration":653,"passed_time":14.00165003,"remaining_time":7.407600779},
{"learn":[1.031495071],"iteration":654,"passed_time":14.02379553,"remaining_time":7.386579326},
{"learn":[1.03143994],"iteration":655,"passed_time":14.04655436,"remaining_time":7.365876065},
{"learn":[1.031380658],"iteration":656,"passed_time":14.06772442,"remaining_time":7.344337102},
{"learn":[1.03131297],"iteration":657,"passed_time":14.08744721,"remaining_time":7.322047032},
{"learn":[1.031203299],"iteration":658,"passed_time":14.10807959,"remaining_time":7.300235419},
{"learn":[1.031103732],"iteration":659,"passed_time":14.1278135,"remaining_time":7.277964529},
{"learn":[1.031001134],"iteration":660,"passed_time":14.14770001,"remaining_time":7.255779583},
{"learn":[1.030960215],"iteration":661,"passed_time":14.16608393,"remaining_time":7.232834395},
{"learn":[1.030840036],"iteration":662,"passed_time":14.1887483,"remaining_time":7.2120787},
{"learn":[1.030785816],"iteration":663,"passed_time":14.20833438,"remaining_time":7.189759568},
{"learn":[1.030702337],"iteration":664,"passed_time":14.22668081,"remaining_time":7.166824166},
{"learn":[1.030676913],"iteration":665,"passed_time":14.24536222,"remaining_time":7.144070544},
{"learn":[1.030610144],"iteration":666,"passed_time":14.26600766,"remaining_time":7.122309672},
{"learn":[1.03048792],"iteration":667,"passed_time":14.29296084,"remaining_time":7.103687123},
{"learn":[1.030434569],"iteration":668,"passed_time":14.31557348,"remaining_time":7.08289211},
{"learn":[1.030411384],"iteration":669,"passed_time":14.33413079,"remaining_time":7.06009427},
{"learn":[1.03032893],"iteration":670,"passed_time":14.35598911,"remaining_time":7.038927596},
{"learn":[1.030294285],"iteration":671,"passed_time":14.37473273,"remaining_time":7.016238596},
{"learn":[1.030207811],"iteration":672,"passed_time":14.39242154,"remaining_time":6.993048801},
{"learn":[1.030103073],"iteration":673,"passed_time":14.41664671,"remaining_time":6.973036836},
{"learn":[1.030087611],"iteration":674,"passed_time":14.43306726,"remaining_time":6.949254605},
{"learn":[1.029976213],"iteration":675,"passed_time":14.45389532,"remaining_time":6.927606631},
{"learn":[1.029859998],"iteration":676,"passed_time":14.47544167,"remaining_time":6.906303781},
{"learn":[1.029811775],"iteration":677,"passed_time":14.49546962,"remaining_time":6.884279082},
{"learn":[1.029739098],"iteration":678,"passed_time":14.5173505,"remaining_time":6.863136244},
{"learn":[1.029682291],"iteration":679,"passed_time":14.53636336,"remaining_time":6.84064158},
{"learn":[1.029651974],"iteration":680,"passed_time":14.55462812,"remaining_time":6.817806713},
{"learn":[1.029587675],"iteration":681,"passed_time":14.57400263,"remaining_time":6.795502691},
{"learn":[1.029450689],"iteration":682,"passed_time":14.59509193,"remaining_time":6.774003137},
{"learn":[1.029382718],"iteration":683,"passed_time":14.61390681,"remaining_time":6.751454024},
{"learn":[1.029251172],"iteration":684,"passed_time":14.63228355,"remaining_time":6.728714335},
{"learn":[1.029161172],"iteration":685,"passed_time":14.64977974,"remaining_time":6.705584311},
{"learn":[1.029054782],"iteration":686,"passed_time":14.67017695,"remaining_time":6.683792409},
{"learn":[1.028995855],"iteration":687,"passed_time":14.6887803,"remaining_time":6.661191065},
{"learn":[1.028948151],"iteration":688,"passed_time":14.71173891,"remaining_time":6.640567201},
{"learn":[1.028861445],"iteration":689,"passed_time":14.73626896,"remaining_time":6.620642576},
{"learn":[1.028738383],"iteration":690,"passed_time":14.75938615,"remaining_time":6.600072821},
{"learn":[1.028672843],"iteration":691,"passed_time":14.77950464,"remaining_time":6.578161025},
{"learn":[1.028624526],"iteration":692,"passed_time":14.80281861,"remaining_time":6.557670003},
{"learn":[1.028563171],"iteration":693,"passed_time":14.82124402,"remaining_time":6.535015373},
{"learn":[1.028440813],"iteration":694,"passed_time":14.84100971,"remaining_time":6.512961095},
{"learn":[1.028374052],"iteration":695,"passed_time":14.86682775,"remaining_time":6.493556949},
{"learn":[1.02829094],"iteration":696,"passed_time":14.88857731,"remaining_time":6.472365744},
{"learn":[1.02821315],"iteration":697,"passed_time":14.90860021,"remaining_time":6.450425881},
{"learn":[1.028135238],"iteration":698,"passed_time":14.92942001,"remaining_time":6.428834656},
{"learn":[1.028071877],"iteration":699,"passed_time":14.94993793,"remaining_time":6.407116256},
{"learn":[1.028040188],"iteration":700,"passed_time":14.97340285,"remaining_time":6.386658277},
{"learn":[1.027940448],"iteration":701,"passed_time":14.99205484,"remaining_time":6.364148634},
{"learn":[1.027885485],"iteration":702,"passed_time":15.01171273,"remaining_time":6.342074939},
{"learn":[1.027772347],"iteration":703,"passed_time":15.03384707,"remaining_time":6.321049336},
{"learn":[1.027679529],"iteration":704,"passed_time":15.0537468,"remaining_time":6.299085542},
{"learn":[1.027600364],"iteration":705,"passed_time":15.07445796,"remaining_time":6.277465496},
{"learn":[1.027551707],"iteration":706,"passed_time":15.09328745,"remaining_time":6.255068207},
{"learn":[1.027472301],"iteration":707,"passed_time":15.11246157,"remaining_time":6.232823134},
{"learn":[1.027389481],"iteration":708,"passed_time":15.13404549,"remaining_time":6.211575795},
{"learn":[1.027301605],"iteration":709,"passed_time":15.1561556,"remaining_time":6.190542428},
{"learn":[1.027210841],"iteration":710,"passed_time":15.17732442,"remaining_time":6.169123429},
{"learn":[1.027162831],"iteration":711,"passed_time":15.19552888,"remaining_time":6.146506064},
{"learn":[1.027123129],"iteration":712,"passed_time":15.21371342,"remaining_time":6.12389306},
{"learn":[1.027006861],"iteration":713,"passed_time":15.23474402,"remaining_time":6.102432479},
{"learn":[1.026880132],"iteration":714,"passed_time":15.2542525,"remaining_time":6.08036638},
{"learn":[1.026796422],"iteration":715,"passed_time":15.2779171,"remaining_time":6.059955943},
{"learn":[1.026758412],"iteration":716,"passed_time":15.30260731,"remaining_time":6.039941241},
{"learn":[1.02672926],"iteration":717,"passed_time":15.31967215,"remaining_time":6.016918588},
{"learn":[1.026594839],"iteration":718,"passed_time":15.34576143,"remaining_time":5.997439446},
{"learn":[1.026561719],"iteration":719,"passed_time":15.3690886,"remaining_time":5.976867787},
{"learn":[1.026517271],"iteration":720,"passed_time":15.39577265,"remaining_time":5.957587473},
{"learn":[1.026422404],"iteration":721,"passed_time":15.42376779,"remaining_time":5.938791476},
{"learn":[1.026336233],"iteration":722,"passed_time":15.44848348,"remaining_time":5.918713587},
{"learn":[1.026232008],"iteration":723,"passed_time":15.47395893,"remaining_time":5.89891252},
{"learn":[1.026143331],"iteration":724,"passed_time":15.49873735,"remaining_time":5.87883141},
{"learn":[1.026084258],"iteration":725,"passed_time":15.52192969,"remaining_time":5.858138752},
{"learn":[1.025987312],"iteration":726,"passed_time":15.55051963,"remaining_time":5.839466106},
{"learn":[1.025916576],"iteration":727,"passed_time":15.57384209,"remaining_time":5.818798143},
{"learn":[1.02587443],"iteration":728,"passed_time":15.59302281,"remaining_time":5.796583239},
{"learn":[1.025770967],"iteration":729,"passed_time":15.61501889,"remaining_time":5.775417946},
{"learn":[1.02570633],"iteration":730,"passed_time":15.63517548,"remaining_time":5.753573468},
{"learn":[1.025651455],"iteration":731,"passed_time":15.65578486,"remaining_time":5.731899377},
{"learn":[1.025530876],"iteration":732,"passed_time":15.68080863,"remaining_time":5.711836157},
{"learn":[1.025456424],"iteration":733,"passed_time":15.70078177,"remaining_time":5.689929088},
{"learn":[1.025358857],"iteration":734,"passed_time":15.72276651,"remaining_time":5.668752552},
{"learn":[1.025293434],"iteration":735,"passed_time":15.7427986,"remaining_time":5.646873411},
{"learn":[1.025223835],"iteration":736,"passed_time":15.77154291,"remaining_time":5.628108256},
{"learn":[1.025127357],"iteration":737,"passed_time":15.79591062,"remaining_time":5.607762308},
{"learn":[1.025044386],"iteration":738,"passed_time":15.81544397,"remaining_time":5.585698072},
{"learn":[1.025002414],"iteration":739,"passed_time":15.83514639,"remaining_time":5.563700084},
{"learn":[1.024939237],"iteration":740,"passed_time":15.85983447,"remaining_time":5.543450915},
{"learn":[1.024846597],"iteration":741,"passed_time":15.88051216,"remaining_time":5.521795333},
{"learn":[1.024751091],"iteration":742,"passed_time":15.90234793,"remaining_time":5.500542958},
{"learn":[1.024712812],"iteration":743,"passed_time":15.9200831,"remaining_time":5.477878056},
{"learn":[1.02464483],"iteration":744,"passed_time":15.94160806,"remaining_time":5.456523563},
{"learn":[1.02456986],"iteration":745,"passed_time":15.96077508,"remaining_time":5.434365777},
{"learn":[1.024520986],"iteration":746,"passed_time":15.98113149,"remaining_time":5.412618832},
{"learn":[1.024408777],"iteration":747,"passed_time":15.99901431,"remaining_time":5.390042253},
{"learn":[1.024335769],"iteration":748,"passed_time":16.01665861,"remaining_time":5.36739828},
{"learn":[1.024309628],"iteration":749,"passed_time":16.03752693,"remaining_time":5.34584231},
{"learn":[1.024238996],"iteration":750,"passed_time":16.05541177,"remaining_time":5.323298975},
{"learn":[1.024111578],"iteration":751,"passed_time":16.08050268,"remaining_time":5.303144499},
{"learn":[1.024006394],"iteration":752,"passed_time":16.09862604,"remaining_time":5.28069141},
{"learn":[1.023961884],"iteration":753,"passed_time":16.1177742,"remaining_time":5.258584156},
{"learn":[1.02391645],"iteration":754,"passed_time":16.13585625,"remaining_time":5.236138782},
{"learn":[1.023854122],"iteration":755,"passed_time":16.15463416,"remaining_time":5.213929543},
{"learn":[1.023763077],"iteration":756,"passed_time":16.17524068,"remaining_time":5.192316361},
{"learn":[1.023639866],"iteration":757,"passed_time":16.19985317,"remaining_time":5.171984786},
{"learn":[1.023581413],"iteration":758,"passed_time":16.2171606,"remaining_time":5.149322403},
{"learn":[1.023502561],"iteration":759,"passed_time":16.23632887,"remaining_time":5.127261748},
{"learn":[1.023428889],"iteration":760,"passed_time":16.25782082,"remaining_time":5.105938472},
{"learn":[1.023350754],"iteration":761,"passed_time":16.28206907,"remaining_time":5.085475643},
{"learn":[1.02328693],"iteration":762,"passed_time":16.30367812,"remaining_time":5.064183111},
{"learn":[1.023171746],"iteration":763,"passed_time":16.32703155,"remaining_time":5.043428594},
{"learn":[1.023057984],"iteration":764,"passed_time":16.34998774,"remaining_time":5.022545252},
{"learn":[1.022950507],"iteration":765,"passed_time":16.37514375,"remaining_time":5.002328509},
{"learn":[1.022830924],"iteration":766,"passed_time":16.39667773,"remaining_time":4.980998579},
{"learn":[1.022754638],"iteration":767,"passed_time":16.41652247,"remaining_time":4.959157831},
{"learn":[1.022703389],"iteration":768,"passed_time":16.43573161,"remaining_time":4.937131343},
{"learn":[1.022652415],"iteration":769,"passed_time":16.45342439,"remaining_time":4.914659233},
{"learn":[1.022524501],"iteration":770,"passed_time":16.4748584,"remaining_time":4.893310731},
{"learn":[1.022465544],"iteration":771,"passed_time":16.49343322,"remaining_time":4.871117583},
{"learn":[1.022394221],"iteration":772,"passed_time":16.51355839,"remaining_time":4.849389076},
{"learn":[1.022341476],"iteration":773,"passed_time":16.53436932,"remaining_time":4.827864945},
{"learn":[1.022319259],"iteration":774,"passed_time":16.55221392,"remaining_time":4.805481461},
{"learn":[1.022206581],"iteration":775,"passed_time":16.57305419,"remaining_time":4.783974406},
{"learn":[1.022044248],"iteration":776,"passed_time":16.59558285,"remaining_time":4.762953636},
{"learn":[1.022001342],"iteration":777,"passed_time":16.61343962,"remaining_time":4.740595882},
{"learn":[1.021908358],"iteration":778,"passed_time":16.64422489,"remaining_time":4.721917459},
{"learn":[1.021827944],"iteration":779,"passed_time":16.66504958,"remaining_time":4.7003986},
{"learn":[1.02169237],"iteration":780,"passed_time":16.68492435,"remaining_time":4.67861515},
{"learn":[1.021585107],"iteration":781,"passed_time":16.70571958,"remaining_time":4.657093182},
{"learn":[1.021540228],"iteration":782,"passed_time":16.7237099,"remaining_time":4.634795719},
{"learn":[1.021509801],"iteration":783,"passed_time":16.74159154,"remaining_time":4.612479303},
{"learn":[1.021490938],"iteration":784,"passed_time":16.75925166,"remaining_time":4.590113512},
{"learn":[1.021392472],"iteration":785,"passed_time":16.78021695,"remaining_time":4.568659578},
{"learn":[1.021280967],"iteration":786,"passed_time":16.80676636,"remaining_time":4.548718214},
{"learn":[1.021188077],"iteration":787,"passed_time":16.82711664,"remaining_time":4.527092295},
{"learn":[1.021152996],"iteration":788,"passed_time":16.84719919,"remaining_time":4.505398009},
{"learn":[1.021076663],"iteration":789,"passed_time":16.86832069,"remaining_time":4.48398398},
{"learn":[1.020998003],"iteration":790,"passed_time":16.88830436,"remaining_time":4.462270051},
{"learn":[1.020885098],"iteration":791,"passed_time":16.90931711,"remaining_time":4.440830756},
{"learn":[1.020731152],"iteration":792,"passed_time":16.93149977,"remaining_time":4.419697922},
{"learn":[1.02068656],"iteration":793,"passed_time":16.95149381,"remaining_time":4.397994616},
{"learn":[1.02061014],"iteration":794,"passed_time":16.97631022,"remaining_time":4.377539114},
{"learn":[1.020568055],"iteration":795,"passed_time":16.99560749,"remaining_time":4.355658201},
{"learn":[1.020491979],"iteration":796,"passed_time":17.0176621,"remaining_time":4.33448608},
{"learn":[1.020396876],"iteration":797,"passed_time":17.04262252,"remaining_time":4.314047305},
{"learn":[1.020306004],"iteration":798,"passed_time":17.06738417,"remaining_time":4.293547206},
{"learn":[1.020204246],"iteration":799,"passed_time":17.08890274,"remaining_time":4.272225686},
{"learn":[1.020113384],"iteration":800,"passed_time":17.11035847,"remaining_time":4.25088806},
{"learn":[1.020028448],"iteration":801,"passed_time":17.13002326,"remaining_time":4.229107987},
{"learn":[1.019966223],"iteration":802,"passed_time":17.15026892,"remaining_time":4.207475687},
{"learn":[1.019924378],"iteration":803,"passed_time":17.16922526,"remaining_time":4.185532526},
{"learn":[1.019871976],"iteration":804,"passed_time":17.18875566,"remaining_time":4.163735844},
{"learn":[1.019826578],"iteration":805,"passed_time":17.20904434,"remaining_time":4.142127298},
{"learn":[1.019799457],"iteration":806,"passed_time":17.22763288,"remaining_time":4.120115423},
{"learn":[1.0197325],"iteration":807,"passed_time":17.24855989,"remaining_time":4.098667696},
{"learn":[1.019693496],"iteration":808,"passed_time":17.27180783,"remaining_time":4.077769215},
{"learn":[1.0196315],"iteration":809,"passed_time":17.29396795,"remaining_time":4.056609766},
{"learn":[1.019551402],"iteration":810,"passed_time":17.31398517,"remaining_time":4.034948455},
{"learn":[1.019482991],"iteration":811,"passed_time":17.33422498,"remaining_time":4.013342729},
{"learn":[1.01942012],"iteration":812,"passed_time":17.35371299,"remaining_time":3.991567439},
{"learn":[1.019368925],"iteration":813,"passed_time":17.37264557,"remaining_time":3.969670855},
{"learn":[1.019272363],"iteration":814,"passed_time":17.39486758,"remaining_time":3.948528224},
{"learn":[1.019237187],"iteration":815,"passed_time":17.41328455,"remaining_time":3.926524947},
{"learn":[1.019210752],"iteration":816,"passed_time":17.43240146,"remaining_time":3.904687231},
{"learn":[1.01917907],"iteration":817,"passed_time":17.4554386,"remaining_time":3.883728393},
{"learn":[1.019108437],"iteration":818,"passed_time":17.47889812,"remaining_time":3.862857827},
{"learn":[1.019049094],"iteration":819,"passed_time":17.50475821,"remaining_time":3.842507901},
{"learn":[1.018976816],"iteration":820,"passed_time":17.52500177,"remaining_time":3.820919997},
{"learn":[1.018872926],"iteration":821,"passed_time":17.54730704,"remaining_time":3.799781816},
{"learn":[1.018783918],"iteration":822,"passed_time":17.57126288,"remaining_time":3.778995784},
{"learn":[1.018661221],"iteration":823,"passed_time":17.59216479,"remaining_time":3.757549761},
{"learn":[1.018535941],"iteration":824,"passed_time":17.6120279,"remaining_time":3.735884706},
{"learn":[1.018447858],"iteration":825,"passed_time":17.63113799,"remaining_time":3.714065388},
{"learn":[1.018406561],"iteration":826,"passed_time":17.65459161,"remaining_time":3.693161244},
{"learn":[1.018342985],"iteration":827,"passed_time":17.67337649,"remaining_time":3.671281107},
{"learn":[1.018321423],"iteration":828,"passed_time":17.69830574,"remaining_time":3.650675852},
{"learn":[1.018250269],"iteration":829,"passed_time":17.71794884,"remaining_time":3.628977473},
{"learn":[1.018178811],"iteration":830,"passed_time":17.73850222,"remaining_time":3.607469164},
{"learn":[1.018119782],"iteration":831,"passed_time":17.75995245,"remaining_time":3.586144245},
{"learn":[1.01801725],"iteration":832,"passed_time":17.78079171,"remaining_time":3.564696537},
{"learn":[1.017912359],"iteration":833,"passed_time":17.80628009,"remaining_time":3.544175653},
{"learn":[1.01783141],"iteration":834,"passed_time":17.83177944,"remaining_time":3.523645039},
{"learn":[1.017796576],"iteration":835,"passed_time":17.8504636,"remaining_time":3.501765587},
{"learn":[1.017713428],"iteration":836,"passed_time":17.87257693,"remaining_time":3.480561576},
{"learn":[1.017680763],"iteration":837,"passed_time":17.89395169,"remaining_time":3.459212618},
{"learn":[1.017607323],"iteration":838,"passed_time":17.91571707,"remaining_time":3.437938555},
{"learn":[1.017534242],"iteration":839,"passed_time":17.93658308,"remaining_time":3.416492016},
{"learn":[1.017487836],"iteration":840,"passed_time":17.95451406,"remaining_time":3.394491956},
{"learn":[1.017448676],"iteration":841,"passed_time":17.97040848,"remaining_time":3.372119406},
{"learn":[1.017355295],"iteration":842,"passed_time":17.9908941,"remaining_time":3.350617287},
{"learn":[1.017200279],"iteration":843,"passed_time":18.01178227,"remaining_time":3.329191984},
{"learn":[1.017118398],"iteration":844,"passed_time":18.03092024,"remaining_time":3.307446907},
{"learn":[1.01703702],"iteration":845,"passed_time":18.05204564,"remaining_time":3.286069774},
{"learn":[1.016929249],"iteration":846,"passed_time":18.07472588,"remaining_time":3.264974096},
{"learn":[1.016873268],"iteration":847,"passed_time":18.09412099,"remaining_time":3.243285838},
{"learn":[1.016803835],"iteration":848,"passed_time":18.11200231,"remaining_time":3.221333743},
{"learn":[1.016719576],"iteration":849,"passed_time":18.13389333,"remaining_time":3.200098823},
{"learn":[1.016697201],"iteration":850,"passed_time":18.15057831,"remaining_time":3.177950844},
{"learn":[1.016610472],"iteration":851,"passed_time":18.17054915,"remaining_time":3.156386472},
{"learn":[1.016555953],"iteration":852,"passed_time":18.18816457,"remaining_time":3.13441992},
{"learn":[1.01648623],"iteration":853,"passed_time":18.20743618,"remaining_time":3.1127467},
{"learn":[1.01640503],"iteration":854,"passed_time":18.22840401,"remaining_time":3.091366762},
{"learn":[1.016283526],"iteration":855,"passed_time":18.26513925,"remaining_time":3.072640248},
{"learn":[1.016256608],"iteration":856,"passed_time":18.28220613,"remaining_time":3.05058982},
{"learn":[1.016203737],"iteration":857,"passed_time":18.30227307,"remaining_time":3.029047525},
{"learn":[1.016171527],"iteration":858,"passed_time":18.3185833,"remaining_time":3.00689202},
{"learn":[1.016094236],"iteration":859,"passed_time":18.34377866,"remaining_time":2.986196526},
{"learn":[1.016035858],"iteration":860,"passed_time":18.36327475,"remaining_time":2.964570488},
{"learn":[1.015978837],"iteration":861,"passed_time":18.3846481,"remaining_time":2.943249928},
{"learn":[1.015907855],"iteration":862,"passed_time":18.40537331,"remaining_time":2.921826355},
{"learn":[1.01584261],"iteration":863,"passed_time":18.4232244,"remaining_time":2.899951989},
{"learn":[1.015775294],"iteration":864,"passed_time":18.4448373,"remaining_time":2.87867403},
{"learn":[1.015700022],"iteration":865,"passed_time":18.46729484,"remaining_time":2.857525992},
{"learn":[1.015646402],"iteration":866,"passed_time":18.48559685,"remaining_time":2.835737463},
{"learn":[1.015600078],"iteration":867,"passed_time":18.50549981,"remaining_time":2.814200432},
{"learn":[1.015537132],"iteration":868,"passed_time":18.52482256,"remaining_time":2.792579695},
{"learn":[1.015482852],"iteration":869,"passed_time":18.54914535,"remaining_time":2.771711374},
{"learn":[1.015346215],"iteration":870,"passed_time":18.57324334,"remaining_time":2.750801827},
{"learn":[1.015303802],"iteration":871,"passed_time":18.59023366,"remaining_time":2.728841638},
{"learn":[1.015254789],"iteration":872,"passed_time":18.6090261,"remaining_time":2.707155},
{"learn":[1.015229426],"iteration":873,"passed_time":18.62878687,"remaining_time":2.685614583},
{"learn":[1.015138097],"iteration":874,"passed_time":18.6499628,"remaining_time":2.664280399},
{"learn":[1.01508886],"iteration":875,"passed_time":18.67171214,"remaining_time":2.643027746},
{"learn":[1.015017523],"iteration":876,"passed_time":18.6909538,"remaining_time":2.621422254},
{"learn":[1.014886819],"iteration":877,"passed_time":18.71356259,"remaining_time":2.600290018},
{"learn":[1.014822986],"iteration":878,"passed_time":18.73704086,"remaining_time":2.579274111},
{"learn":[1.01472433],"iteration":879,"passed_time":18.76064356,"remaining_time":2.558269576},
{"learn":[1.014659627],"iteration":880,"passed_time":18.77982293,"remaining_time":2.536661667},
{"learn":[1.014590514],"iteration":881,"passed_time":18.79990095,"remaining_time":2.515179492},
{"learn":[1.014491764],"iteration":882,"passed_time":18.8228949,"remaining_time":2.494086867},
{"learn":[1.014411941],"iteration":883,"passed_time":18.84832142,"remaining_time":2.473309146},
{"learn":[1.014336952],"iteration":884,"passed_time":18.86802357,"remaining_time":2.451777074},
{"learn":[1.014268657],"iteration":885,"passed_time":18.89013176,"remaining_time":2.430558713},
{"learn":[1.01421605],"iteration":886,"passed_time":18.90923335,"remaining_time":2.40895532},
{"learn":[1.014169455],"iteration":887,"passed_time":18.9264594,"remaining_time":2.387121005},
{"learn":[1.014141974],"iteration":888,"passed_time":18.94609318,"remaining_time":2.365597686},
{"learn":[1.014076996],"iteration":889,"passed_time":18.96678277,"remaining_time":2.344209107},
{"learn":[1.014004981],"iteration":890,"passed_time":18.9893275,"remaining_time":2.323049043},
{"learn":[1.013988754],"iteration":891,"passed_time":19.00642921,"remaining_time":2.301226855},
{"learn":[1.013915799],"iteration":892,"passed_time":19.02843133,"remaining_time":2.280002411},
{"learn":[1.0138551],"iteration":893,"passed_time":19.04928628,"remaining_time":2.258640208},
{"learn":[1.013796912],"iteration":894,"passed_time":19.06705768,"remaining_time":2.236917382},
{"learn":[1.013701459],"iteration":895,"passed_time":19.08602159,"remaining_time":2.215341791},
{"learn":[1.013667606],"iteration":896,"passed_time":19.10355403,"remaining_time":2.193607653},
{"learn":[1.013614627],"iteration":897,"passed_time":19.12260359,"remaining_time":2.172055196},
{"learn":[1.013540976],"iteration":898,"passed_time":19.14615143,"remaining_time":2.151013676},
{"learn":[1.01350501],"iteration":899,"passed_time":19.16349913,"remaining_time":2.129277681},
{"learn":[1.013461104],"iteration":900,"passed_time":19.18542521,"remaining_time":2.10805449},
{"learn":[1.013421012],"iteration":901,"passed_time":19.20714722,"remaining_time":2.08680757},
{"learn":[1.013330192],"iteration":902,"passed_time":19.23027046,"remaining_time":2.065710116},
{"learn":[1.013276148],"iteration":903,"passed_time":19.25534749,"remaining_time":2.044815663},
{"learn":[1.013257351],"iteration":904,"passed_time":19.27199391,"remaining_time":2.023026985},
{"learn":[1.013154171],"iteration":905,"passed_time":19.29317797,"remaining_time":2.001720451},
{"learn":[1.013105316],"iteration":906,"passed_time":19.31258318,"remaining_time":1.980231792},
{"learn":[1.013068383],"iteration":907,"passed_time":19.33162017,"remaining_time":1.958710413},
{"learn":[1.012971422],"iteration":908,"passed_time":19.35280338,"remaining_time":1.937409359},
{"learn":[1.012850676],"iteration":909,"passed_time":19.37197512,"remaining_time":1.915909627},
{"learn":[1.01274574],"iteration":910,"passed_time":19.39510902,"remaining_time":1.894802088},
{"learn":[1.012707831],"iteration":911,"passed_time":19.41612737,"remaining_time":1.873485974},
{"learn":[1.012579895],"iteration":912,"passed_time":19.43885162,"remaining_time":1.852333068},
{"learn":[1.012512692],"iteration":913,"passed_time":19.46030737,"remaining_time":1.831057368},
{"learn":[1.012410171],"iteration":914,"passed_time":19.47908111,"remaining_time":1.809532125},
{"learn":[1.012370125],"iteration":915,"passed_time":19.49744251,"remaining_time":1.787975078},
{"learn":[1.012302397],"iteration":916,"passed_time":19.51559542,"remaining_time":1.766406128},
{"learn":[1.012262625],"iteration":917,"passed_time":19.53557921,"remaining_time":1.745008165},
{"learn":[1.012217775],"iteration":918,"passed_time":19.56101481,"remaining_time":1.724093797},
{"learn":[1.012099024],"iteration":919,"passed_time":19.58306805,"remaining_time":1.702875482},
{"learn":[1.012044711],"iteration":920,"passed_time":19.60780986,"remaining_time":1.681885971},
{"learn":[1.01197086],"iteration":921,"passed_time":19.6290721,"remaining_time":1.660593952},
{"learn":[1.011878593],"iteration":922,"passed_time":19.64896892,"remaining_time":1.63918809},
{"learn":[1.011806382],"iteration":923,"passed_time":19.66905165,"remaining_time":1.617800785},
{"learn":[1.011732689],"iteration":924,"passed_time":19.68718763,"remaining_time":1.596258456},
{"learn":[1.011672955],"iteration":925,"passed_time":19.70920175,"remaining_time":1.575033401},
{"learn":[1.011580019],"iteration":926,"passed_time":19.73010527,"remaining_time":1.553719185},
{"learn":[1.011481076],"iteration":927,"passed_time":19.75214268,"remaining_time":1.532493828},
{"learn":[1.011380628],"iteration":928,"passed_time":19.77197113,"remaining_time":1.511097902},
{"learn":[1.011293462],"iteration":929,"passed_time":19.79090954,"remaining_time":1.489638352},
{"learn":[1.011237448],"iteration":930,"passed_time":19.81505606,"remaining_time":1.468570213},
{"learn":[1.011210888],"iteration":931,"passed_time":19.83464044,"remaining_time":1.447162608},
{"learn":[1.011136286],"iteration":932,"passed_time":19.85800535,"remaining_time":1.426030395},
{"learn":[1.011050227],"iteration":933,"passed_time":19.88145692,"remaining_time":1.404899525},
{"learn":[1.01101712],"iteration":934,"passed_time":19.90175403,"remaining_time":1.383544398},
{"learn":[1.010959128],"iteration":935,"passed_time":19.91999393,"remaining_time":1.362050867},
{"learn":[1.010929921],"iteration":936,"passed_time":19.93825581,"remaining_time":1.340565759},
{"learn":[1.010892539],"iteration":937,"passed_time":19.95535398,"remaining_time":1.319010604},
{"learn":[1.010838752],"iteration":938,"passed_time":19.9748122,"remaining_time":1.297618258},
{"learn":[1.010727642],"iteration":939,"passed_time":19.99476118,"remaining_time":1.276261352},
{"learn":[1.010642586],"iteration":940,"passed_time":20.01451325,"remaining_time":1.254895092},
{"learn":[1.010562433],"iteration":941,"passed_time":20.0383764,"remaining_time":1.233785383},
{"learn":[1.010483512],"iteration":942,"passed_time":20.05818067,"remaining_time":1.212424494},
{"learn":[1.010435505],"iteration":943,"passed_time":20.07662912,"remaining_time":1.190986473},
{"learn":[1.010359533],"iteration":944,"passed_time":20.09513776,"remaining_time":1.169558282},
{"learn":[1.010202461],"iteration":945,"passed_time":20.11641506,"remaining_time":1.148294306},
{"learn":[1.010165032],"iteration":946,"passed_time":20.13844907,"remaining_time":1.127072651},
{"learn":[1.010055916],"iteration":947,"passed_time":20.16122298,"remaining_time":1.105889868},
{"learn":[1.01002108],"iteration":948,"passed_time":20.18039012,"remaining_time":1.084509901},
{"learn":[1.009965464],"iteration":949,"passed_time":20.20038026,"remaining_time":1.063177909},
{"learn":[1.009894446],"iteration":950,"passed_time":20.23134827,"remaining_time":1.042414369},
{"learn":[1.009836841],"iteration":951,"passed_time":20.25293621,"remaining_time":1.021156448},
{"learn":[1.009740078],"iteration":952,"passed_time":20.27328507,"remaining_time":0.9998367242},
{"learn":[1.009676158],"iteration":953,"passed_time":20.29576807,"remaining_time":0.9786219407},
{"learn":[1.009631149],"iteration":954,"passed_time":20.31510412,"remaining_time":0.957256215},
{"learn":[1.00957272],"iteration":955,"passed_time":20.33861051,"remaining_time":0.9360866764},
{"learn":[1.009495279],"iteration":956,"passed_time":20.36068808,"remaining_time":0.9148480539},
{"learn":[1.009416648],"iteration":957,"passed_time":20.38318942,"remaining_time":0.8936262585},
{"learn":[1.0093234],"iteration":958,"passed_time":20.4081443,"remaining_time":0.8725066904},
{"learn":[1.009311637],"iteration":959,"passed_time":20.42579541,"remaining_time":0.8510748088},
{"learn":[1.009247121],"iteration":960,"passed_time":20.45631226,"remaining_time":0.8301729222},
{"learn":[1.009209516],"iteration":961,"passed_time":20.48003638,"remaining_time":0.808982726},
{"learn":[1.009149842],"iteration":962,"passed_time":20.50400222,"remaining_time":0.7877965548},
{"learn":[1.009054966],"iteration":963,"passed_time":20.53140022,"remaining_time":0.7667327882},
{"learn":[1.008960035],"iteration":964,"passed_time":20.56054749,"remaining_time":0.7457193389},
{"learn":[1.008913951],"iteration":965,"passed_time":20.58344361,"remaining_time":0.7244690299},
{"learn":[1.008882933],"iteration":966,"passed_time":20.60252367,"remaining_time":0.7030850891},
{"learn":[1.008755697],"iteration":967,"passed_time":20.62379277,"remaining_time":0.6817782733},
{"learn":[1.008700125],"iteration":968,"passed_time":20.64527324,"remaining_time":0.6604782975},
{"learn":[1.008594078],"iteration":969,"passed_time":20.67090245,"remaining_time":0.6393062613},
{"learn":[1.008561511],"iteration":970,"passed_time":20.69284999,"remaining_time":0.6180150873},
{"learn":[1.008494607],"iteration":971,"passed_time":20.71524409,"remaining_time":0.5967354266},
{"learn":[1.008411213],"iteration":972,"passed_time":20.73897552,"remaining_time":0.5754905848},
{"learn":[1.008332426],"iteration":973,"passed_time":20.76194282,"remaining_time":0.5542202397},
{"learn":[1.008254495],"iteration":974,"passed_time":20.78366359,"remaining_time":0.532914451},
{"learn":[1.008197992],"iteration":975,"passed_time":20.80877336,"remaining_time":0.5116911481},
{"learn":[1.008130144],"iteration":976,"passed_time":20.82925783,"remaining_time":0.4903510033},
{"learn":[1.008055979],"iteration":977,"passed_time":20.85457023,"remaining_time":0.4691212118},
{"learn":[1.007998835],"iteration":978,"passed_time":20.87854733,"remaining_time":0.447854437},
{"learn":[1.007859564],"iteration":979,"passed_time":20.90241659,"remaining_time":0.4265799303},
{"learn":[1.007821716],"iteration":980,"passed_time":20.92534537,"remaining_time":0.4052819185},
{"learn":[1.007794421],"iteration":981,"passed_time":20.94422596,"remaining_time":0.3839063821},
{"learn":[1.007750406],"iteration":982,"passed_time":20.96166942,"remaining_time":0.3625110684},
{"learn":[1.007702028],"iteration":983,"passed_time":20.9825275,"remaining_time":0.341179309},
{"learn":[1.007644871],"iteration":984,"passed_time":21.00073006,"remaining_time":0.319808072},
{"learn":[1.007507428],"iteration":985,"passed_time":21.02178771,"remaining_time":0.2984838012},
{"learn":[1.007405557],"iteration":986,"passed_time":21.04597698,"remaining_time":0.2772013179},
{"learn":[1.007319672],"iteration":987,"passed_time":21.07020627,"remaining_time":0.2559134364},
{"learn":[1.007262314],"iteration":988,"passed_time":21.09715116,"remaining_time":0.2346498107},
{"learn":[1.007222953],"iteration":989,"passed_time":21.11558674,"remaining_time":0.213288755},
{"learn":[1.007131158],"iteration":990,"passed_time":21.1389739,"remaining_time":0.1919785723},
{"learn":[1.007060977],"iteration":991,"passed_time":21.15855145,"remaining_time":0.1706334794},
{"learn":[1.007006529],"iteration":992,"passed_time":21.17731853,"remaining_time":0.1492862333},
{"learn":[1.006907988],"iteration":993,"passed_time":21.19617191,"remaining_time":0.1279446996},
{"learn":[1.006857601],"iteration":994,"passed_time":21.22013456,"remaining_time":0.106633842},
{"learn":[1.006777502],"iteration":995,"passed_time":21.23942075,"remaining_time":0.0852988785},
{"learn":[1.006676731],"iteration":996,"passed_time":21.26145988,"remaining_time":0.06397630855},
{"learn":[1.006634758],"iteration":997,"passed_time":21.28176736,"remaining_time":0.04264883239},
{"learn":[1.006608102],"iteration":998,"passed_time":21.30150885,"remaining_time":0.02132283169},
{"learn":[1.006472713],"iteration":999,"passed_time":21.32428295,"remaining_time":0}
]}